{
 "_readme": "Generated by tools/build_coauthors.py from authors.json. Do not edit by hand -- rerun the script after authors.json changes. An ego network with the site owner removed: nodes are his most frequent co-authors, sized by shared-paper count ('papers'), shaded by length of collaboration -- the 'span' in years from first to latest shared paper -- on a light->dark ramp ('color'); 'pale' marks a fill light enough that its label flips to dark ink. edges weight how many papers two co-authors share with each other (on a big consortium/hub paper only its lead and senior authors count). 'x','y','r' are precomputed layout coordinates (arbitrary units; the page derives its viewBox from them). 'keys' are '<section-id>|<number>' matching publications.html so a node can filter the publication list.",
 "generatedFrom": "authors.json",
 "nodes": [
  {
   "id": "madhav-marathe",
   "name": "Madhav Marathe",
   "short": "Marathe",
   "papers": 70,
   "inst": "University of Virginia",
   "color": "#104281",
   "span": 9,
   "firstYear": 2017,
   "lastYear": 2026,
   "x": 145.71,
   "y": 270.52,
   "r": 46.0,
   "keys": [
    "book-chapters|1",
    "book-chapters|2",
    "book-chapters|3",
    "conference-papers|10",
    "conference-papers|11",
    "conference-papers|12",
    "conference-papers|14",
    "conference-papers|18",
    "conference-papers|19",
    "conference-papers|20",
    "conference-papers|21",
    "conference-papers|22",
    "conference-papers|23",
    "conference-papers|24",
    "conference-papers|25",
    "conference-papers|26",
    "conference-papers|28",
    "conference-papers|29",
    "conference-papers|30",
    "conference-papers|32",
    "conference-papers|33",
    "conference-papers|34",
    "conference-papers|36",
    "conference-papers|37",
    "conference-papers|38",
    "conference-papers|39",
    "conference-papers|40",
    "journal-articles|11",
    "journal-articles|12",
    "journal-articles|13",
    "journal-articles|14",
    "journal-articles|15",
    "journal-articles|17",
    "journal-articles|18",
    "journal-articles|20",
    "journal-articles|21",
    "journal-articles|22",
    "journal-articles|23",
    "journal-articles|24",
    "journal-articles|26",
    "journal-articles|27",
    "journal-articles|29",
    "journal-articles|3",
    "journal-articles|30",
    "journal-articles|31",
    "journal-articles|32",
    "journal-articles|33",
    "journal-articles|34",
    "journal-articles|35",
    "journal-articles|36",
    "journal-articles|37",
    "journal-articles|39",
    "journal-articles|4",
    "journal-articles|40",
    "journal-articles|41",
    "journal-articles|42",
    "journal-articles|43",
    "journal-articles|7",
    "journal-articles|8",
    "journal-articles|9",
    "tech-reports|11",
    "tech-reports|12",
    "tech-reports|13",
    "tech-reports|14",
    "tech-reports|4",
    "tech-reports|5",
    "tech-reports|6",
    "tech-reports|7",
    "tech-reports|8",
    "tech-reports|9"
   ]
  },
  {
   "id": "bryan-lewis",
   "name": "Bryan Lewis",
   "short": "Lewis",
   "papers": 59,
   "inst": "University of Virginia",
   "color": "#104281",
   "span": 9,
   "firstYear": 2017,
   "lastYear": 2026,
   "x": 288.54,
   "y": -115.44,
   "r": 43.38,
   "keys": [
    "book-chapters|1",
    "book-chapters|2",
    "book-chapters|3",
    "conference-papers|10",
    "conference-papers|11",
    "conference-papers|19",
    "conference-papers|20",
    "conference-papers|21",
    "conference-papers|23",
    "conference-papers|24",
    "conference-papers|25",
    "conference-papers|28",
    "conference-papers|29",
    "conference-papers|30",
    "conference-papers|32",
    "conference-papers|33",
    "conference-papers|34",
    "conference-papers|36",
    "conference-papers|38",
    "conference-papers|39",
    "journal-articles|10",
    "journal-articles|11",
    "journal-articles|12",
    "journal-articles|13",
    "journal-articles|15",
    "journal-articles|17",
    "journal-articles|18",
    "journal-articles|20",
    "journal-articles|21",
    "journal-articles|22",
    "journal-articles|24",
    "journal-articles|26",
    "journal-articles|27",
    "journal-articles|28",
    "journal-articles|29",
    "journal-articles|3",
    "journal-articles|30",
    "journal-articles|31",
    "journal-articles|32",
    "journal-articles|33",
    "journal-articles|34",
    "journal-articles|35",
    "journal-articles|36",
    "journal-articles|37",
    "journal-articles|39",
    "journal-articles|4",
    "journal-articles|40",
    "journal-articles|41",
    "journal-articles|42",
    "journal-articles|43",
    "journal-articles|7",
    "journal-articles|8",
    "tech-reports|12",
    "tech-reports|13",
    "tech-reports|14",
    "tech-reports|4",
    "tech-reports|5",
    "tech-reports|8",
    "tech-reports|9"
   ]
  },
  {
   "id": "jiangzhuo-chen",
   "name": "Jiangzhuo Chen",
   "short": "Chen",
   "papers": 40,
   "inst": "University of Virginia",
   "color": "#104281",
   "span": 9,
   "firstYear": 2017,
   "lastYear": 2026,
   "x": 234.4,
   "y": 341.1,
   "r": 38.17,
   "keys": [
    "book-chapters|1",
    "book-chapters|3",
    "conference-papers|10",
    "conference-papers|11",
    "conference-papers|19",
    "conference-papers|20",
    "conference-papers|21",
    "conference-papers|22",
    "conference-papers|24",
    "conference-papers|25",
    "conference-papers|26",
    "conference-papers|28",
    "conference-papers|36",
    "journal-articles|12",
    "journal-articles|13",
    "journal-articles|14",
    "journal-articles|17",
    "journal-articles|18",
    "journal-articles|20",
    "journal-articles|21",
    "journal-articles|22",
    "journal-articles|26",
    "journal-articles|28",
    "journal-articles|29",
    "journal-articles|3",
    "journal-articles|30",
    "journal-articles|32",
    "journal-articles|34",
    "journal-articles|35",
    "journal-articles|36",
    "journal-articles|4",
    "journal-articles|41",
    "journal-articles|42",
    "journal-articles|7",
    "journal-articles|8",
    "tech-reports|10",
    "tech-reports|13",
    "tech-reports|4",
    "tech-reports|5",
    "tech-reports|8"
   ]
  },
  {
   "id": "aniruddha-adiga",
   "name": "Aniruddha Adiga",
   "short": "Adiga",
   "papers": 34,
   "inst": "University of Virginia",
   "color": "#2a78d6",
   "span": 6,
   "firstYear": 2020,
   "lastYear": 2026,
   "x": 61.4,
   "y": 67.34,
   "r": 36.27,
   "keys": [
    "book-chapters|1",
    "book-chapters|2",
    "book-chapters|3",
    "conference-papers|19",
    "conference-papers|20",
    "conference-papers|22",
    "conference-papers|23",
    "conference-papers|26",
    "conference-papers|29",
    "conference-papers|30",
    "conference-papers|33",
    "conference-papers|37",
    "conference-papers|40",
    "journal-articles|14",
    "journal-articles|15",
    "journal-articles|18",
    "journal-articles|21",
    "journal-articles|22",
    "journal-articles|23",
    "journal-articles|24",
    "journal-articles|26",
    "journal-articles|27",
    "journal-articles|29",
    "journal-articles|30",
    "journal-articles|32",
    "journal-articles|33",
    "journal-articles|34",
    "journal-articles|39",
    "journal-articles|40",
    "tech-reports|11",
    "tech-reports|14",
    "tech-reports|4",
    "tech-reports|5",
    "tech-reports|9"
   ]
  },
  {
   "id": "anil-vullikanti",
   "name": "Anil Vullikanti",
   "short": "Vullikanti",
   "papers": 26,
   "inst": "University of Virginia",
   "color": "#0d366b",
   "span": 10,
   "firstYear": 2016,
   "lastYear": 2026,
   "x": 469.24,
   "y": 194.09,
   "r": 33.42,
   "keys": [
    "book-chapters|2",
    "conference-papers|10",
    "conference-papers|16",
    "conference-papers|20",
    "conference-papers|25",
    "conference-papers|28",
    "conference-papers|36",
    "conference-papers|41",
    "conference-papers|7",
    "journal-articles|12",
    "journal-articles|13",
    "journal-articles|14",
    "journal-articles|15",
    "journal-articles|17",
    "journal-articles|18",
    "journal-articles|20",
    "journal-articles|21",
    "journal-articles|22",
    "journal-articles|29",
    "journal-articles|32",
    "journal-articles|34",
    "journal-articles|35",
    "journal-articles|4",
    "journal-articles|8",
    "tech-reports|5",
    "tech-reports|8"
   ]
  },
  {
   "id": "henning-mortveit",
   "name": "Henning Mortveit",
   "short": "Mortveit",
   "papers": 24,
   "inst": "University of Virginia",
   "color": "#184f95",
   "span": 8,
   "firstYear": 2017,
   "lastYear": 2025,
   "x": 356.41,
   "y": -53.6,
   "r": 32.63,
   "keys": [
    "book-chapters|1",
    "conference-papers|10",
    "conference-papers|21",
    "conference-papers|24",
    "conference-papers|25",
    "conference-papers|28",
    "conference-papers|32",
    "conference-papers|34",
    "conference-papers|38",
    "conference-papers|39",
    "journal-articles|13",
    "journal-articles|14",
    "journal-articles|20",
    "journal-articles|21",
    "journal-articles|26",
    "journal-articles|30",
    "journal-articles|31",
    "journal-articles|32",
    "journal-articles|35",
    "journal-articles|36",
    "journal-articles|41",
    "journal-articles|8",
    "tech-reports|4",
    "tech-reports|8"
   ]
  },
  {
   "id": "przemyslaw-porebski",
   "name": "Przemyslaw Porebski",
   "short": "Porebski",
   "papers": 21,
   "inst": "University of Virginia",
   "color": "#2a78d6",
   "span": 6,
   "firstYear": 2020,
   "lastYear": 2026,
   "x": 201.69,
   "y": -76.93,
   "r": 31.39,
   "keys": [
    "book-chapters|1",
    "conference-papers|18",
    "conference-papers|23",
    "conference-papers|25",
    "conference-papers|29",
    "conference-papers|30",
    "conference-papers|33",
    "journal-articles|18",
    "journal-articles|21",
    "journal-articles|22",
    "journal-articles|24",
    "journal-articles|26",
    "journal-articles|27",
    "journal-articles|30",
    "journal-articles|32",
    "journal-articles|33",
    "journal-articles|34",
    "journal-articles|35",
    "journal-articles|42",
    "tech-reports|13",
    "tech-reports|4"
   ]
  },
  {
   "id": "christopher-l-barrett",
   "name": "Christopher L. Barrett",
   "short": "Barrett",
   "papers": 17,
   "inst": "University of Virginia",
   "color": "#5598e7",
   "span": 4,
   "firstYear": 2020,
   "lastYear": 2024,
   "x": 451.1,
   "y": 72.08,
   "r": 29.56,
   "keys": [
    "conference-papers|21",
    "conference-papers|24",
    "conference-papers|25",
    "conference-papers|28",
    "conference-papers|32",
    "journal-articles|11",
    "journal-articles|13",
    "journal-articles|17",
    "journal-articles|20",
    "journal-articles|21",
    "journal-articles|29",
    "journal-articles|31",
    "journal-articles|35",
    "journal-articles|41",
    "tech-reports|12",
    "tech-reports|4",
    "tech-reports|8"
   ],
   "pale": true
  },
  {
   "id": "lijing-wang",
   "name": "Lijing Wang",
   "short": "Wang",
   "papers": 16,
   "inst": "University of Virginia",
   "color": "#5598e7",
   "span": 4,
   "firstYear": 2020,
   "lastYear": 2024,
   "x": 120.44,
   "y": 121.34,
   "r": 29.07,
   "keys": [
    "book-chapters|2",
    "book-chapters|3",
    "conference-papers|19",
    "conference-papers|20",
    "conference-papers|22",
    "conference-papers|23",
    "conference-papers|26",
    "conference-papers|29",
    "conference-papers|30",
    "journal-articles|17",
    "journal-articles|18",
    "journal-articles|24",
    "journal-articles|27",
    "journal-articles|28",
    "journal-articles|33",
    "tech-reports|5"
   ],
   "pale": true
  },
  {
   "id": "stefan-hoops",
   "name": "Stefan Hoops",
   "short": "Hoops",
   "papers": 16,
   "inst": "University of Virginia",
   "color": "#5598e7",
   "span": 4,
   "firstYear": 2020,
   "lastYear": 2024,
   "x": 242.72,
   "y": 266.3,
   "r": 29.07,
   "keys": [
    "conference-papers|21",
    "conference-papers|24",
    "conference-papers|25",
    "conference-papers|28",
    "journal-articles|13",
    "journal-articles|20",
    "journal-articles|21",
    "journal-articles|22",
    "journal-articles|26",
    "journal-articles|30",
    "journal-articles|32",
    "journal-articles|35",
    "journal-articles|36",
    "journal-articles|41",
    "tech-reports|4",
    "tech-reports|8"
   ],
   "pale": true
  },
  {
   "id": "benjamin-hurt",
   "name": "Benjamin Hurt",
   "short": "Hurt",
   "papers": 15,
   "inst": "University of Virginia",
   "color": "#6da7ec",
   "span": 3,
   "firstYear": 2021,
   "lastYear": 2024,
   "x": 94.09,
   "y": 0.07,
   "r": 28.55,
   "keys": [
    "conference-papers|23",
    "conference-papers|29",
    "conference-papers|30",
    "conference-papers|33",
    "journal-articles|18",
    "journal-articles|21",
    "journal-articles|22",
    "journal-articles|24",
    "journal-articles|26",
    "journal-articles|27",
    "journal-articles|30",
    "journal-articles|32",
    "journal-articles|33",
    "journal-articles|34",
    "journal-articles|39"
   ],
   "pale": true
  },
  {
   "id": "parantapa-bhattacharya",
   "name": "Parantapa Bhattacharya",
   "short": "Bhattacharya",
   "papers": 14,
   "inst": "University of Virginia",
   "color": "#5598e7",
   "span": 4,
   "firstYear": 2020,
   "lastYear": 2024,
   "x": 212.49,
   "y": 206.39,
   "r": 28.02,
   "keys": [
    "conference-papers|18",
    "conference-papers|21",
    "conference-papers|25",
    "conference-papers|28",
    "journal-articles|12",
    "journal-articles|21",
    "journal-articles|22",
    "journal-articles|26",
    "journal-articles|30",
    "journal-articles|32",
    "journal-articles|35",
    "journal-articles|36",
    "journal-articles|41",
    "tech-reports|8"
   ],
   "pale": true
  },
  {
   "id": "samarth-swarup",
   "name": "Samarth Swarup",
   "short": "Swarup",
   "papers": 13,
   "inst": "University of Virginia",
   "color": "#3987e5",
   "span": 5,
   "firstYear": 2020,
   "lastYear": 2025,
   "x": 96.36,
   "y": -65.28,
   "r": 27.47,
   "keys": [
    "conference-papers|20",
    "conference-papers|24",
    "conference-papers|32",
    "conference-papers|34",
    "conference-papers|38",
    "conference-papers|39",
    "journal-articles|21",
    "journal-articles|23",
    "journal-articles|29",
    "journal-articles|31",
    "tech-reports|5",
    "tech-reports|7",
    "tech-reports|9"
   ]
  },
  {
   "id": "shaun-truelove",
   "name": "Shaun Truelove",
   "short": "Truelove",
   "papers": 13,
   "inst": "Johns Hopkins University",
   "color": "#3987e5",
   "span": 5,
   "firstYear": 2021,
   "lastYear": 2026,
   "x": -302.02,
   "y": 34.39,
   "r": 27.47,
   "keys": [
    "journal-articles|18",
    "journal-articles|22",
    "journal-articles|24",
    "journal-articles|26",
    "journal-articles|30",
    "journal-articles|32",
    "journal-articles|33",
    "journal-articles|37",
    "journal-articles|38",
    "journal-articles|39",
    "journal-articles|42",
    "tech-reports|13",
    "tech-reports|14"
   ]
  },
  {
   "id": "abhijin-adiga",
   "name": "Abhijin Adiga",
   "short": "Adiga",
   "papers": 12,
   "inst": "University of Virginia",
   "color": "#184f95",
   "span": 8,
   "firstYear": 2016,
   "lastYear": 2024,
   "x": 389.59,
   "y": 187.23,
   "r": 26.89,
   "keys": [
    "conference-papers|12",
    "conference-papers|14",
    "conference-papers|24",
    "conference-papers|25",
    "conference-papers|28",
    "conference-papers|7",
    "journal-articles|16",
    "journal-articles|21",
    "journal-articles|35",
    "journal-articles|36",
    "journal-articles|9",
    "tech-reports|8"
   ]
  },
  {
   "id": "alessandro-vespignani",
   "name": "Alessandro Vespignani",
   "short": "Vespignani",
   "papers": 12,
   "inst": "Northeastern University",
   "color": "#3987e5",
   "span": 5,
   "firstYear": 2021,
   "lastYear": 2026,
   "x": -609.37,
   "y": 15.7,
   "r": 26.89,
   "keys": [
    "journal-articles|18",
    "journal-articles|19",
    "journal-articles|22",
    "journal-articles|24",
    "journal-articles|26",
    "journal-articles|28",
    "journal-articles|30",
    "journal-articles|32",
    "journal-articles|33",
    "journal-articles|39",
    "journal-articles|42",
    "tech-reports|13"
   ]
  },
  {
   "id": "dustin-machi",
   "name": "Dustin Machi",
   "short": "Machi",
   "papers": 12,
   "inst": "University of Virginia",
   "color": "#5598e7",
   "span": 4,
   "firstYear": 2020,
   "lastYear": 2024,
   "x": 265.82,
   "y": -39.49,
   "r": 26.89,
   "keys": [
    "conference-papers|18",
    "conference-papers|21",
    "conference-papers|25",
    "journal-articles|21",
    "journal-articles|22",
    "journal-articles|26",
    "journal-articles|30",
    "journal-articles|32",
    "journal-articles|35",
    "journal-articles|36",
    "journal-articles|41",
    "tech-reports|4"
   ],
   "pale": true
  },
  {
   "id": "mandy-wilson",
   "name": "Mandy Wilson",
   "short": "Wilson",
   "papers": 12,
   "inst": "University of Virginia",
   "color": "#5598e7",
   "span": 4,
   "firstYear": 2020,
   "lastYear": 2024,
   "x": 429.19,
   "y": 134.46,
   "r": 26.89,
   "keys": [
    "conference-papers|18",
    "conference-papers|21",
    "conference-papers|24",
    "conference-papers|25",
    "conference-papers|28",
    "journal-articles|21",
    "journal-articles|28",
    "journal-articles|34",
    "journal-articles|35",
    "journal-articles|41",
    "tech-reports|4",
    "tech-reports|8"
   ],
   "pale": true
  },
  {
   "id": "matteo-chinazzi",
   "name": "Matteo Chinazzi",
   "short": "Chinazzi",
   "papers": 12,
   "inst": "Northeastern University",
   "color": "#3987e5",
   "span": 5,
   "firstYear": 2021,
   "lastYear": 2026,
   "x": -323.68,
   "y": -88.62,
   "r": 26.89,
   "keys": [
    "journal-articles|18",
    "journal-articles|22",
    "journal-articles|24",
    "journal-articles|26",
    "journal-articles|28",
    "journal-articles|30",
    "journal-articles|32",
    "journal-articles|33",
    "journal-articles|38",
    "journal-articles|39",
    "journal-articles|42",
    "tech-reports|13"
   ]
  },
  {
   "id": "achla-marathe",
   "name": "Achla Marathe",
   "short": "Marathe",
   "papers": 11,
   "inst": "University of Virginia",
   "color": "#1c5cab",
   "span": 7,
   "firstYear": 2017,
   "lastYear": 2024,
   "x": 305.68,
   "y": 300.97,
   "r": 26.28,
   "keys": [
    "conference-papers|12",
    "conference-papers|14",
    "conference-papers|25",
    "conference-papers|28",
    "journal-articles|13",
    "journal-articles|20",
    "journal-articles|21",
    "journal-articles|35",
    "journal-articles|9",
    "tech-reports|10",
    "tech-reports|8"
   ]
  },
  {
   "id": "ajitesh-srivastava",
   "name": "Ajitesh Srivastava",
   "short": "Srivastava",
   "papers": 11,
   "inst": "University of Southern California",
   "color": "#5598e7",
   "span": 4,
   "firstYear": 2021,
   "lastYear": 2025,
   "x": -33.62,
   "y": -148.25,
   "r": 26.28,
   "keys": [
    "journal-articles|18",
    "journal-articles|22",
    "journal-articles|24",
    "journal-articles|26",
    "journal-articles|27",
    "journal-articles|30",
    "journal-articles|32",
    "journal-articles|33",
    "journal-articles|38",
    "journal-articles|39",
    "journal-articles|42"
   ],
   "pale": true
  },
  {
   "id": "brian-klahn",
   "name": "Brian Klahn",
   "short": "Klahn",
   "papers": 11,
   "inst": "University of Virginia",
   "color": "#5598e7",
   "span": 4,
   "firstYear": 2020,
   "lastYear": 2024,
   "x": 315.68,
   "y": 3.94,
   "r": 26.28,
   "keys": [
    "conference-papers|18",
    "conference-papers|25",
    "journal-articles|18",
    "journal-articles|21",
    "journal-articles|22",
    "journal-articles|26",
    "journal-articles|30",
    "journal-articles|32",
    "journal-articles|34",
    "journal-articles|35",
    "tech-reports|4"
   ],
   "pale": true
  },
  {
   "id": "c-cile-viboud",
   "name": "Cécile Viboud",
   "short": "Viboud",
   "papers": 11,
   "inst": "Fogarty International Center",
   "color": "#3987e5",
   "span": 5,
   "firstYear": 2021,
   "lastYear": 2026,
   "x": -461.84,
   "y": 80.18,
   "r": 26.28,
   "keys": [
    "journal-articles|18",
    "journal-articles|19",
    "journal-articles|22",
    "journal-articles|26",
    "journal-articles|30",
    "journal-articles|32",
    "journal-articles|37",
    "journal-articles|38",
    "journal-articles|39",
    "journal-articles|42",
    "tech-reports|13"
   ]
  },
  {
   "id": "jessica-t-davis",
   "name": "Jessica T. Davis",
   "short": "Davis",
   "papers": 11,
   "inst": "Northeastern University",
   "color": "#3987e5",
   "span": 5,
   "firstYear": 2021,
   "lastYear": 2026,
   "x": -58.69,
   "y": -45.55,
   "r": 26.28,
   "keys": [
    "journal-articles|18",
    "journal-articles|22",
    "journal-articles|24",
    "journal-articles|26",
    "journal-articles|28",
    "journal-articles|30",
    "journal-articles|32",
    "journal-articles|33",
    "journal-articles|39",
    "journal-articles|42",
    "tech-reports|13"
   ]
  },
  {
   "id": "justin-lessler",
   "name": "Justin Lessler",
   "short": "Lessler",
   "papers": 11,
   "inst": "University of North Carolina at Chapel Hill",
   "color": "#3987e5",
   "span": 5,
   "firstYear": 2021,
   "lastYear": 2026,
   "x": -403.67,
   "y": -30.02,
   "r": 26.28,
   "keys": [
    "journal-articles|18",
    "journal-articles|22",
    "journal-articles|24",
    "journal-articles|26",
    "journal-articles|30",
    "journal-articles|32",
    "journal-articles|33",
    "journal-articles|37",
    "journal-articles|39",
    "journal-articles|42",
    "tech-reports|13"
   ]
  },
  {
   "id": "stephen-eubank",
   "name": "Stephen Eubank",
   "short": "Eubank",
   "papers": 11,
   "inst": "University of Virginia",
   "color": "#2a78d6",
   "span": 6,
   "firstYear": 2017,
   "lastYear": 2023,
   "x": 267.12,
   "y": 164.05,
   "r": 26.28,
   "keys": [
    "conference-papers|12",
    "conference-papers|14",
    "conference-papers|28",
    "journal-articles|11",
    "journal-articles|13",
    "journal-articles|20",
    "journal-articles|21",
    "journal-articles|28",
    "journal-articles|9",
    "tech-reports|4",
    "tech-reports|8"
   ]
  },
  {
   "id": "matthew-biggerstaff",
   "name": "Matthew Biggerstaff",
   "short": "Biggerstaff",
   "papers": 10,
   "inst": "Centers for Disease Control and Prevention",
   "color": "#6da7ec",
   "span": 3,
   "firstYear": 2021,
   "lastYear": 2024,
   "x": -589.94,
   "y": -52.44,
   "r": 25.63,
   "keys": [
    "journal-articles|17",
    "journal-articles|18",
    "journal-articles|19",
    "journal-articles|22",
    "journal-articles|24",
    "journal-articles|26",
    "journal-articles|28",
    "journal-articles|30",
    "journal-articles|33",
    "journal-articles|39"
   ],
   "pale": true
  },
  {
   "id": "joseph-outten",
   "name": "Joseph Outten",
   "short": "Outten",
   "papers": 9,
   "inst": "University of Virginia",
   "color": "#6da7ec",
   "span": 3,
   "firstYear": 2021,
   "lastYear": 2024,
   "x": 187.53,
   "y": 100.45,
   "r": 24.95,
   "keys": [
    "conference-papers|25",
    "conference-papers|36",
    "journal-articles|18",
    "journal-articles|21",
    "journal-articles|22",
    "journal-articles|26",
    "journal-articles|30",
    "journal-articles|32",
    "journal-articles|35"
   ],
   "pale": true
  },
  {
   "id": "ana-pastore-y-piontti",
   "name": "Ana Pastore y Piontti",
   "short": "Piontti",
   "papers": 8,
   "inst": "Northeastern University",
   "color": "#6da7ec",
   "span": 3,
   "firstYear": 2021,
   "lastYear": 2024,
   "x": -282.06,
   "y": -137.01,
   "r": 24.21,
   "keys": [
    "journal-articles|18",
    "journal-articles|22",
    "journal-articles|24",
    "journal-articles|26",
    "journal-articles|28",
    "journal-articles|30",
    "journal-articles|33",
    "journal-articles|39"
   ],
   "pale": true
  },
  {
   "id": "emily-howerton",
   "name": "Emily Howerton",
   "short": "Howerton",
   "papers": 8,
   "inst": "Pennsylvania State University",
   "color": "#3987e5",
   "span": 5,
   "firstYear": 2021,
   "lastYear": 2026,
   "x": -519.04,
   "y": 45.57,
   "r": 24.21,
   "keys": [
    "journal-articles|18",
    "journal-articles|22",
    "journal-articles|26",
    "journal-articles|30",
    "journal-articles|32",
    "journal-articles|37",
    "journal-articles|42",
    "tech-reports|13"
   ]
  },
  {
   "id": "harry-hochheiser",
   "name": "Harry Hochheiser",
   "short": "Hochheiser",
   "papers": 8,
   "inst": "University of Pittsburgh",
   "color": "#5598e7",
   "span": 4,
   "firstYear": 2022,
   "lastYear": 2026,
   "x": 7.35,
   "y": 16.47,
   "r": 24.21,
   "keys": [
    "journal-articles|22",
    "journal-articles|26",
    "journal-articles|30",
    "journal-articles|32",
    "journal-articles|37",
    "journal-articles|42",
    "tech-reports|13",
    "tech-reports|14"
   ],
   "pale": true
  },
  {
   "id": "katriona-shea",
   "name": "Katriona Shea",
   "short": "Shea",
   "papers": 8,
   "inst": "Pennsylvania State University",
   "color": "#3987e5",
   "span": 5,
   "firstYear": 2021,
   "lastYear": 2026,
   "x": -472.92,
   "y": -32.22,
   "r": 24.21,
   "keys": [
    "journal-articles|18",
    "journal-articles|22",
    "journal-articles|26",
    "journal-articles|30",
    "journal-articles|32",
    "journal-articles|37",
    "journal-articles|42",
    "tech-reports|13"
   ]
  },
  {
   "id": "nicholas-g-reich",
   "name": "Nicholas G Reich",
   "short": "Reich",
   "papers": 8,
   "inst": "University of Massachusetts Amherst",
   "color": "#6da7ec",
   "span": 3,
   "firstYear": 2021,
   "lastYear": 2024,
   "x": -534.06,
   "y": -86.56,
   "r": 24.21,
   "keys": [
    "journal-articles|18",
    "journal-articles|19",
    "journal-articles|24",
    "journal-articles|26",
    "journal-articles|27",
    "journal-articles|30",
    "journal-articles|33",
    "journal-articles|39"
   ],
   "pale": true
  },
  {
   "id": "adam-sadilek",
   "name": "Adam Sadilek",
   "short": "Sadilek",
   "papers": 7,
   "inst": "Google (United States)",
   "color": "#86b6ef",
   "span": 2,
   "firstYear": 2020,
   "lastYear": 2022,
   "x": 52.81,
   "y": 134.81,
   "r": 23.41,
   "keys": [
    "book-chapters|3",
    "conference-papers|20",
    "conference-papers|22",
    "conference-papers|26",
    "journal-articles|17",
    "tech-reports|5",
    "tech-reports|6"
   ],
   "pale": true
  },
  {
   "id": "anurag-kumar",
   "name": "Anurag Kumar",
   "short": "Kumar",
   "papers": 7,
   "inst": "Indian Institute of Science Bangalore",
   "color": "#5598e7",
   "span": 4,
   "firstYear": 2010,
   "lastYear": 2014,
   "x": -198.14,
   "y": -163.89,
   "r": 23.41,
   "keys": [
    "conference-papers|1",
    "conference-papers|2",
    "conference-papers|3",
    "conference-papers|4",
    "journal-articles|1",
    "tech-reports|1",
    "tech-reports|2"
   ],
   "pale": true
  },
  {
   "id": "dah-ming-chiu",
   "name": "Dah Ming Chiu",
   "short": "Chiu",
   "papers": 7,
   "inst": "Chinese University of Hong Kong",
   "color": "#6da7ec",
   "span": 3,
   "firstYear": 2015,
   "lastYear": 2018,
   "x": -213.67,
   "y": 1.93,
   "r": 23.41,
   "keys": [
    "conference-papers|13",
    "conference-papers|5",
    "conference-papers|6",
    "conference-papers|8",
    "journal-articles|2",
    "journal-articles|5",
    "journal-articles|6"
   ],
   "pale": true
  },
  {
   "id": "jeffrey-shaman",
   "name": "Jeffrey Shaman",
   "short": "Shaman",
   "papers": 7,
   "inst": "Columbia University",
   "color": "#86b6ef",
   "span": 2,
   "firstYear": 2022,
   "lastYear": 2024,
   "x": -16.24,
   "y": -91.56,
   "r": 23.41,
   "keys": [
    "journal-articles|22",
    "journal-articles|24",
    "journal-articles|26",
    "journal-articles|28",
    "journal-articles|30",
    "journal-articles|33",
    "journal-articles|39"
   ],
   "pale": true
  },
  {
   "id": "lauren-ancel-meyers",
   "name": "Lauren Ancel Meyers",
   "short": "Meyers",
   "papers": 7,
   "inst": "The University of Texas at Austin",
   "color": "#5598e7",
   "span": 4,
   "firstYear": 2022,
   "lastYear": 2026,
   "x": -170.46,
   "y": -39.19,
   "r": 23.41,
   "keys": [
    "journal-articles|24",
    "journal-articles|28",
    "journal-articles|30",
    "journal-articles|32",
    "journal-articles|39",
    "journal-articles|42",
    "tech-reports|13"
   ],
   "pale": true
  },
  {
   "id": "michael-a-johansson",
   "name": "Michael A. Johansson",
   "short": "Johansson",
   "papers": 7,
   "inst": "Centers for Disease Control and Prevention",
   "color": "#6da7ec",
   "span": 3,
   "firstYear": 2021,
   "lastYear": 2024,
   "x": -533.99,
   "y": -10.58,
   "r": 23.41,
   "keys": [
    "journal-articles|18",
    "journal-articles|19",
    "journal-articles|22",
    "journal-articles|24",
    "journal-articles|26",
    "journal-articles|30",
    "journal-articles|33"
   ],
   "pale": true
  },
  {
   "id": "michael-c-runge",
   "name": "Michael C. Runge",
   "short": "Runge",
   "papers": 7,
   "inst": "United States Geological Survey",
   "color": "#5598e7",
   "span": 4,
   "firstYear": 2021,
   "lastYear": 2025,
   "x": -393.32,
   "y": 82.15,
   "r": 23.41,
   "keys": [
    "journal-articles|18",
    "journal-articles|22",
    "journal-articles|26",
    "journal-articles|30",
    "journal-articles|32",
    "journal-articles|37",
    "journal-articles|42"
   ],
   "pale": true
  },
  {
   "id": "sen-pei",
   "name": "Sen Pei",
   "short": "Pei",
   "papers": 7,
   "inst": "Columbia University",
   "color": "#86b6ef",
   "span": 2,
   "firstYear": 2022,
   "lastYear": 2024,
   "x": -255.51,
   "y": -188.65,
   "r": 23.41,
   "keys": [
    "journal-articles|22",
    "journal-articles|24",
    "journal-articles|26",
    "journal-articles|28",
    "journal-articles|30",
    "journal-articles|33",
    "journal-articles|39"
   ],
   "pale": true
  },
  {
   "id": "zakaria-mehrab",
   "name": "Zakaria Mehrab",
   "short": "Mehrab",
   "papers": 7,
   "inst": "University of Virginia",
   "color": "#3987e5",
   "span": 5,
   "firstYear": 2020,
   "lastYear": 2025,
   "x": 207.57,
   "y": -9.16,
   "r": 23.41,
   "keys": [
    "conference-papers|32",
    "conference-papers|34",
    "conference-papers|38",
    "conference-papers|39",
    "journal-articles|23",
    "journal-articles|31",
    "tech-reports|7"
   ]
  },
  {
   "id": "akhil-sai-peddireddy",
   "name": "Akhil Sai Peddireddy",
   "short": "Peddireddy",
   "papers": 6,
   "inst": "University of Virginia",
   "color": "#5598e7",
   "span": 4,
   "firstYear": 2020,
   "lastYear": 2024,
   "x": 362.75,
   "y": 46.31,
   "r": 22.52,
   "keys": [
    "conference-papers|18",
    "conference-papers|23",
    "journal-articles|18",
    "journal-articles|24",
    "journal-articles|33",
    "tech-reports|4"
   ],
   "pale": true
  },
  {
   "id": "andrew-warren",
   "name": "Andrew Warren",
   "short": "Warren",
   "papers": 6,
   "inst": "University of Virginia",
   "color": "#2a78d6",
   "span": 6,
   "firstYear": 2020,
   "lastYear": 2026,
   "x": 154.98,
   "y": 172.52,
   "r": 22.52,
   "keys": [
    "conference-papers|36",
    "journal-articles|21",
    "journal-articles|29",
    "journal-articles|40",
    "journal-articles|43",
    "tech-reports|4"
   ]
  },
  {
   "id": "dawen-xie",
   "name": "Dawen Xie",
   "short": "Xie",
   "papers": 6,
   "inst": "University of Virginia",
   "color": "#5598e7",
   "span": 4,
   "firstYear": 2020,
   "lastYear": 2024,
   "x": 243.82,
   "y": 73.17,
   "r": 22.52,
   "keys": [
    "conference-papers|18",
    "conference-papers|24",
    "conference-papers|25",
    "journal-articles|21",
    "journal-articles|35",
    "tech-reports|4"
   ],
   "pale": true
  },
  {
   "id": "gursharn-kaur",
   "name": "Gursharn Kaur",
   "short": "Kaur",
   "papers": 6,
   "inst": "University of Virginia",
   "color": "#86b6ef",
   "span": 2,
   "firstYear": 2022,
   "lastYear": 2024,
   "x": 139.26,
   "y": 63.8,
   "r": 22.52,
   "keys": [
    "conference-papers|29",
    "conference-papers|30",
    "conference-papers|33",
    "journal-articles|33",
    "journal-articles|39",
    "journal-articles|40"
   ],
   "pale": true
  },
  {
   "id": "rebecca-k-borchering",
   "name": "Rebecca K. Borchering",
   "short": "Borchering",
   "papers": 6,
   "inst": "Pennsylvania State University",
   "color": "#6da7ec",
   "span": 3,
   "firstYear": 2021,
   "lastYear": 2024,
   "x": -460.22,
   "y": 22.37,
   "r": 22.52,
   "keys": [
    "journal-articles|18",
    "journal-articles|22",
    "journal-articles|26",
    "journal-articles|30",
    "journal-articles|37",
    "journal-articles|39"
   ],
   "pale": true
  },
  {
   "id": "sara-l-loo",
   "name": "Sara L. Loo",
   "short": "Loo",
   "papers": 6,
   "inst": "Johns Hopkins University",
   "color": "#6da7ec",
   "span": 3,
   "firstYear": 2023,
   "lastYear": 2026,
   "x": -397.46,
   "y": 27.37,
   "r": 22.52,
   "keys": [
    "journal-articles|30",
    "journal-articles|32",
    "journal-articles|38",
    "journal-articles|39",
    "journal-articles|42",
    "tech-reports|13"
   ],
   "pale": true
  },
  {
   "id": "baltazar-espinoza",
   "name": "Baltazar Espinoza",
   "short": "Espinoza",
   "papers": 5,
   "inst": "University of Virginia",
   "color": "#6da7ec",
   "span": 3,
   "firstYear": 2023,
   "lastYear": 2026,
   "x": 332.66,
   "y": 91.23,
   "r": 21.51,
   "keys": [
    "conference-papers|36",
    "conference-papers|41",
    "journal-articles|29",
    "journal-articles|40",
    "journal-articles|43"
   ],
   "pale": true
  },
  {
   "id": "dave-higdon",
   "name": "Dave Higdon",
   "short": "Higdon",
   "papers": 5,
   "inst": "Virginia Tech",
   "color": "#5598e7",
   "span": 4,
   "firstYear": 2017,
   "lastYear": 2021,
   "x": 363.86,
   "y": 135.97,
   "r": 21.51,
   "keys": [
    "conference-papers|11",
    "journal-articles|17",
    "journal-articles|4",
    "journal-articles|7",
    "journal-articles|8"
   ],
   "pale": true
  },
  {
   "id": "david-leblang",
   "name": "David Leblang",
   "short": "Leblang",
   "papers": 5,
   "inst": "University of Virginia",
   "color": "#86b6ef",
   "span": 1,
   "firstYear": 2024,
   "lastYear": 2025,
   "x": 151.51,
   "y": -33.06,
   "r": 21.51,
   "keys": [
    "conference-papers|32",
    "conference-papers|34",
    "conference-papers|38",
    "conference-papers|39",
    "journal-articles|31"
   ],
   "pale": true
  },
  {
   "id": "nikos-i-bosse",
   "name": "Nikos I Bosse",
   "short": "Bosse",
   "papers": 5,
   "inst": "London School of Hygiene & Tropical Medicine",
   "color": "#5598e7",
   "span": 4,
   "firstYear": 2022,
   "lastYear": 2026,
   "x": -808.7,
   "y": -113.25,
   "r": 21.51,
   "keys": [
    "journal-articles|24",
    "journal-articles|25",
    "journal-articles|27",
    "journal-articles|39",
    "journal-articles|44"
   ],
   "pale": true
  },
  {
   "id": "rajesh-sundaresan",
   "name": "Rajesh Sundaresan",
   "short": "Sundaresan",
   "papers": 5,
   "inst": "Indian Institute of Science Bangalore",
   "color": "#86b6ef",
   "span": 2,
   "firstYear": 2021,
   "lastYear": 2023,
   "x": 61.99,
   "y": 235.07,
   "r": 21.51,
   "keys": [
    "conference-papers|22",
    "conference-papers|33",
    "journal-articles|29",
    "tech-reports|11",
    "tech-reports|9"
   ],
   "pale": true
  },
  {
   "id": "amanda-wilson",
   "name": "Amanda Wilson",
   "short": "Wilson",
   "papers": 4,
   "inst": "University of Virginia",
   "color": "#86b6ef",
   "span": 1,
   "firstYear": 2022,
   "lastYear": 2023,
   "x": -284.64,
   "y": -43.35,
   "r": 20.32,
   "keys": [
    "book-chapters|1",
    "journal-articles|26",
    "journal-articles|30",
    "journal-articles|32"
   ],
   "pale": true
  },
  {
   "id": "arindam-fadikar",
   "name": "Arindam Fadikar",
   "short": "Fadikar",
   "papers": 4,
   "inst": "Argonne National Laboratory",
   "color": "#6da7ec",
   "span": 3,
   "firstYear": 2018,
   "lastYear": 2021,
   "x": 277.23,
   "y": 217.34,
   "r": 20.32,
   "keys": [
    "conference-papers|21",
    "journal-articles|17",
    "journal-articles|7",
    "journal-articles|8"
   ],
   "pale": true
  },
  {
   "id": "erik-rosenstrom",
   "name": "Erik Rosenstrom",
   "short": "Rosenstrom",
   "papers": 4,
   "inst": "North Carolina State University",
   "color": "#86b6ef",
   "span": 2,
   "firstYear": 2022,
   "lastYear": 2024,
   "x": -114.82,
   "y": -18.22,
   "r": 20.32,
   "keys": [
    "journal-articles|24",
    "journal-articles|30",
    "journal-articles|32",
    "journal-articles|37"
   ],
   "pale": true
  },
  {
   "id": "justin-crow",
   "name": "Justin Crow",
   "short": "Crow",
   "papers": 4,
   "inst": "Virginia Department of Health",
   "color": "#6da7ec",
   "span": 3,
   "firstYear": 2021,
   "lastYear": 2024,
   "x": 255.15,
   "y": 22.44,
   "r": 20.32,
   "keys": [
    "book-chapters|1",
    "conference-papers|24",
    "journal-articles|40",
    "tech-reports|12"
   ],
   "pale": true
  },
  {
   "id": "katie-yan",
   "name": "Katie Yan",
   "short": "Yan",
   "papers": 4,
   "inst": "Pennsylvania State University",
   "color": "#6da7ec",
   "span": 3,
   "firstYear": 2023,
   "lastYear": 2026,
   "x": -97.65,
   "y": -145.39,
   "r": 20.32,
   "keys": [
    "journal-articles|32",
    "journal-articles|37",
    "journal-articles|42",
    "tech-reports|13"
   ],
   "pale": true
  },
  {
   "id": "logan-stundal",
   "name": "Logan Stundal",
   "short": "Stundal",
   "papers": 4,
   "inst": "University of Virginia",
   "color": "#86b6ef",
   "span": 1,
   "firstYear": 2024,
   "lastYear": 2025,
   "x": 183.52,
   "y": -137.15,
   "r": 20.32,
   "keys": [
    "conference-papers|32",
    "conference-papers|34",
    "conference-papers|38",
    "journal-articles|31"
   ],
   "pale": true
  },
  {
   "id": "marta-galanti",
   "name": "Marta Galanti",
   "short": "Galanti",
   "papers": 4,
   "inst": "Columbia University",
   "color": "#86b6ef",
   "span": 1,
   "firstYear": 2022,
   "lastYear": 2023,
   "x": -76.22,
   "y": -98.67,
   "r": 20.32,
   "keys": [
    "journal-articles|22",
    "journal-articles|26",
    "journal-articles|28",
    "journal-articles|30"
   ],
   "pale": true
  },
  {
   "id": "sam-abbott",
   "name": "Sam Abbott",
   "short": "Abbott",
   "papers": 4,
   "inst": "London School of Hygiene & Tropical Medicine",
   "color": "#5598e7",
   "span": 4,
   "firstYear": 2022,
   "lastYear": 2026,
   "x": -772.52,
   "y": -237.64,
   "r": 20.32,
   "keys": [
    "journal-articles|24",
    "journal-articles|25",
    "journal-articles|27",
    "journal-articles|44"
   ],
   "pale": true
  },
  {
   "id": "siva-athreya",
   "name": "Siva Athreya",
   "short": "Athreya",
   "papers": 4,
   "inst": "Indian Statistical Institute",
   "color": "#86b6ef",
   "span": 2,
   "firstYear": 2021,
   "lastYear": 2023,
   "x": 109.12,
   "y": 203.21,
   "r": 20.32,
   "keys": [
    "conference-papers|33",
    "journal-articles|29",
    "tech-reports|11",
    "tech-reports|9"
   ],
   "pale": true
  },
  {
   "id": "thomas-mcandrew",
   "name": "Thomas McAndrew",
   "short": "McAndrew",
   "papers": 4,
   "inst": "Lehigh University",
   "color": "#5598e7",
   "span": 4,
   "firstYear": 2022,
   "lastYear": 2026,
   "x": -832.13,
   "y": -185.22,
   "r": 20.32,
   "keys": [
    "journal-articles|24",
    "journal-articles|25",
    "journal-articles|39",
    "journal-articles|44"
   ],
   "pale": true
  },
  {
   "id": "yan-wu",
   "name": "Yan Wu",
   "short": "Wu",
   "papers": 4,
   "inst": "Chinese University of Hong Kong",
   "color": "#6da7ec",
   "span": 3,
   "firstYear": 2015,
   "lastYear": 2018,
   "x": -258.87,
   "y": -87.87,
   "r": 20.32,
   "keys": [
    "conference-papers|6",
    "conference-papers|8",
    "journal-articles|2",
    "journal-articles|5"
   ],
   "pale": true
  },
  {
   "id": "abhishek-pandey",
   "name": "Abhishek Pandey",
   "short": "Pandey",
   "papers": 3,
   "inst": "Yale University",
   "color": "#86b6ef",
   "span": 0,
   "firstYear": 2024,
   "lastYear": 2024,
   "x": 140.03,
   "y": -258.67,
   "r": 18.76,
   "keys": [
    "conference-papers|32",
    "conference-papers|34",
    "journal-articles|31"
   ],
   "pale": true
  },
  {
   "id": "alison-p-galvani",
   "name": "Alison P. Galvani",
   "short": "Galvani",
   "papers": 3,
   "inst": "Yale University",
   "color": "#86b6ef",
   "span": 0,
   "firstYear": 2024,
   "lastYear": 2024,
   "x": 89.38,
   "y": -189.87,
   "r": 18.76,
   "keys": [
    "conference-papers|32",
    "conference-papers|34",
    "journal-articles|31"
   ],
   "pale": true
  },
  {
   "id": "alok-talekar",
   "name": "Alok Talekar",
   "short": "Talekar",
   "papers": 3,
   "inst": "Google (United States)",
   "color": "#86b6ef",
   "span": 1,
   "firstYear": 2020,
   "lastYear": 2021,
   "x": -13.43,
   "y": 64.94,
   "r": 18.76,
   "keys": [
    "conference-papers|20",
    "conference-papers|22",
    "tech-reports|5"
   ],
   "pale": true
  },
  {
   "id": "ashish-v-tendulkar",
   "name": "Ashish V. Tendulkar",
   "short": "Tendulkar",
   "papers": 3,
   "inst": "Google (United States)",
   "color": "#86b6ef",
   "span": 1,
   "firstYear": 2020,
   "lastYear": 2021,
   "x": -50.7,
   "y": 99.48,
   "r": 18.76,
   "keys": [
    "conference-papers|20",
    "conference-papers|22",
    "tech-reports|5"
   ],
   "pale": true
  },
  {
   "id": "b-aditya-prakash",
   "name": "B. Aditya Prakash",
   "short": "Prakash",
   "papers": 3,
   "inst": "Georgia Institute of Technology",
   "color": "#6da7ec",
   "span": 3,
   "firstYear": 2020,
   "lastYear": 2023,
   "x": -134.86,
   "y": -182.02,
   "r": 18.76,
   "keys": [
    "conference-papers|16",
    "journal-articles|24",
    "journal-articles|39"
   ],
   "pale": true
  },
  {
   "id": "burton-h-singer",
   "name": "Burton H. Singer",
   "short": "Singer",
   "papers": 3,
   "inst": "University of Florida",
   "color": "#86b6ef",
   "span": 0,
   "firstYear": 2024,
   "lastYear": 2024,
   "x": 91.48,
   "y": -237.09,
   "r": 18.76,
   "keys": [
    "conference-papers|32",
    "conference-papers|34",
    "journal-articles|31"
   ],
   "pale": true
  },
  {
   "id": "chad-r-wells",
   "name": "Chad R. Wells",
   "short": "Wells",
   "papers": 3,
   "inst": "Yale University",
   "color": "#86b6ef",
   "span": 0,
   "firstYear": 2024,
   "lastYear": 2024,
   "x": 185.81,
   "y": -232.34,
   "r": 18.76,
   "keys": [
    "conference-papers|32",
    "conference-papers|34",
    "journal-articles|31"
   ],
   "pale": true
  },
  {
   "id": "gaia-dempsey",
   "name": "Gaia Dempsey",
   "short": "Dempsey",
   "papers": 3,
   "inst": "Metaculus",
   "color": "#5598e7",
   "span": 4,
   "firstYear": 2022,
   "lastYear": 2026,
   "x": -666.58,
   "y": -142.18,
   "r": 18.76,
   "keys": [
    "journal-articles|25",
    "journal-articles|44",
    "tech-reports|12"
   ],
   "pale": true
  },
  {
   "id": "gaurav-aggarwal",
   "name": "Gaurav Aggarwal",
   "short": "Aggarwal",
   "papers": 3,
   "inst": "Google (United States)",
   "color": "#86b6ef",
   "span": 1,
   "firstYear": 2020,
   "lastYear": 2021,
   "x": -33.32,
   "y": 144.36,
   "r": 18.76,
   "keys": [
    "conference-papers|20",
    "conference-papers|22",
    "tech-reports|5"
   ],
   "pale": true
  },
  {
   "id": "h-vincent-poor",
   "name": "H. Vincent Poor",
   "short": "Poor",
   "papers": 3,
   "inst": "Princeton University",
   "color": "#5598e7",
   "span": 4,
   "firstYear": 2022,
   "lastYear": 2026,
   "x": 297.47,
   "y": 53.98,
   "r": 18.76,
   "keys": [
    "book-chapters|2",
    "journal-articles|29",
    "journal-articles|43"
   ],
   "pale": true
  },
  {
   "id": "james-schlitt",
   "name": "James Schlitt",
   "short": "Schlitt",
   "papers": 3,
   "inst": "University of Virginia",
   "color": "#6da7ec",
   "span": 3,
   "firstYear": 2020,
   "lastYear": 2023,
   "x": 389.39,
   "y": 92.27,
   "r": 18.76,
   "keys": [
    "journal-articles|18",
    "journal-articles|28",
    "tech-reports|4"
   ],
   "pale": true
  },
  {
   "id": "juan-cambeiro",
   "name": "Juan Cambeiro",
   "short": "Cambeiro",
   "papers": 3,
   "inst": "Columbia University",
   "color": "#5598e7",
   "span": 4,
   "firstYear": 2022,
   "lastYear": 2026,
   "x": -696.97,
   "y": -180.54,
   "r": 18.76,
   "keys": [
    "journal-articles|25",
    "journal-articles|44",
    "tech-reports|12"
   ],
   "pale": true
  },
  {
   "id": "mark-orr",
   "name": "Mark Orr",
   "short": "Orr",
   "papers": 3,
   "inst": "University of Virginia",
   "color": "#6da7ec",
   "span": 3,
   "firstYear": 2020,
   "lastYear": 2023,
   "x": 415.72,
   "y": 23.91,
   "r": 18.76,
   "keys": [
    "journal-articles|28",
    "tech-reports|12",
    "tech-reports|4"
   ],
   "pale": true
  },
  {
   "id": "milind-tambe",
   "name": "Milind Tambe",
   "short": "Tambe",
   "papers": 3,
   "inst": "Google (United States)",
   "color": "#86b6ef",
   "span": 1,
   "firstYear": 2020,
   "lastYear": 2021,
   "x": 2.44,
   "y": 109.39,
   "r": 18.76,
   "keys": [
    "conference-papers|20",
    "conference-papers|22",
    "tech-reports|5"
   ],
   "pale": true
  },
  {
   "id": "naren-ramakrishnan",
   "name": "Naren Ramakrishnan",
   "short": "Ramakrishnan",
   "papers": 3,
   "inst": "Virginia Tech",
   "color": "#104281",
   "span": 9,
   "firstYear": 2017,
   "lastYear": 2026,
   "x": -228.68,
   "y": -46.9,
   "r": 18.76,
   "keys": [
    "conference-papers|41",
    "journal-articles|3",
    "journal-articles|39"
   ]
  },
  {
   "id": "nihesh-rathod",
   "name": "Nihesh Rathod",
   "short": "Rathod",
   "papers": 3,
   "inst": "Indian Institute of Science Bangalore",
   "color": "#86b6ef",
   "span": 2,
   "firstYear": 2021,
   "lastYear": 2023,
   "x": 7.3,
   "y": 250.72,
   "r": 18.76,
   "keys": [
    "conference-papers|33",
    "tech-reports|11",
    "tech-reports|9"
   ],
   "pale": true
  },
  {
   "id": "pyrros-a-telionis",
   "name": "Pyrros A. Telionis",
   "short": "Telionis",
   "papers": 3,
   "inst": "University of Virginia",
   "color": "#86b6ef",
   "span": 1,
   "firstYear": 2020,
   "lastYear": 2021,
   "x": 265.59,
   "y": -211.48,
   "r": 18.76,
   "keys": [
    "journal-articles|10",
    "journal-articles|18",
    "tech-reports|4"
   ],
   "pale": true
  },
  {
   "id": "qiu-fang-ying",
   "name": "Qiu Fang Ying",
   "short": "Ying",
   "papers": 3,
   "inst": "Chinese University of Hong Kong",
   "color": "#6da7ec",
   "span": 3,
   "firstYear": 2015,
   "lastYear": 2018,
   "x": -118.25,
   "y": -65.87,
   "r": 18.76,
   "keys": [
    "conference-papers|13",
    "conference-papers|5",
    "journal-articles|6"
   ],
   "pale": true
  },
  {
   "id": "r-muniappan",
   "name": "R. Muniappan",
   "short": "Muniappan",
   "papers": 3,
   "inst": "Virginia Tech",
   "color": "#6da7ec",
   "span": 3,
   "firstYear": 2017,
   "lastYear": 2020,
   "x": 460.37,
   "y": -28.86,
   "r": 18.76,
   "keys": [
    "conference-papers|12",
    "journal-articles|16",
    "journal-articles|9"
   ],
   "pale": true
  },
  {
   "id": "rita-r-colwell",
   "name": "Rita R. Colwell",
   "short": "Colwell",
   "papers": 3,
   "inst": "University of Maryland, College Park",
   "color": "#86b6ef",
   "span": 0,
   "firstYear": 2024,
   "lastYear": 2024,
   "x": 137.03,
   "y": -211.95,
   "r": 18.76,
   "keys": [
    "conference-papers|32",
    "conference-papers|34",
    "journal-articles|31"
   ],
   "pale": true
  },
  {
   "id": "s-s-ravi",
   "name": "S. S. Ravi",
   "short": "Ravi",
   "papers": 3,
   "inst": "University of Virginia",
   "color": "#6da7ec",
   "span": 3,
   "firstYear": 2022,
   "lastYear": 2025,
   "x": 156.31,
   "y": 15.88,
   "r": 18.76,
   "keys": [
    "book-chapters|2",
    "conference-papers|38",
    "conference-papers|39"
   ],
   "pale": true
  },
  {
   "id": "sarath-yasodharan",
   "name": "Sarath Yasodharan",
   "short": "Yasodharan",
   "papers": 3,
   "inst": "Indian Institute of Science Bangalore",
   "color": "#86b6ef",
   "span": 2,
   "firstYear": 2021,
   "lastYear": 2023,
   "x": 57.85,
   "y": 185.18,
   "r": 18.76,
   "keys": [
    "conference-papers|33",
    "tech-reports|11",
    "tech-reports|9"
   ],
   "pale": true
  },
  {
   "id": "sasikiran-kandula",
   "name": "Sasikiran Kandula",
   "short": "Kandula",
   "papers": 3,
   "inst": "Columbia University",
   "color": "#86b6ef",
   "span": 2,
   "firstYear": 2021,
   "lastYear": 2023,
   "x": -645.95,
   "y": -29.08,
   "r": 18.76,
   "keys": [
    "journal-articles|19",
    "journal-articles|28",
    "journal-articles|39"
   ],
   "pale": true
  },
  {
   "id": "simon-a-levin",
   "name": "Simon A. Levin",
   "short": "Levin",
   "papers": 3,
   "inst": "Princeton University",
   "color": "#5598e7",
   "span": 4,
   "firstYear": 2022,
   "lastYear": 2026,
   "x": 195.19,
   "y": 48.34,
   "r": 18.76,
   "keys": [
    "book-chapters|2",
    "journal-articles|29",
    "journal-articles|43"
   ],
   "pale": true
  },
  {
   "id": "wen-you",
   "name": "Wen You",
   "short": "You",
   "papers": 3,
   "inst": "University of Virginia",
   "color": "#86b6ef",
   "span": 1,
   "firstYear": 2020,
   "lastYear": 2021,
   "x": 332.71,
   "y": 211.43,
   "r": 18.76,
   "keys": [
    "journal-articles|13",
    "journal-articles|20",
    "tech-reports|10"
   ],
   "pale": true
  },
  {
   "id": "xue-ben",
   "name": "Xue Ben",
   "short": "Ben",
   "papers": 3,
   "inst": "Google (United States)",
   "color": "#86b6ef",
   "span": 0,
   "firstYear": 2020,
   "lastYear": 2020,
   "x": -28.81,
   "y": 190.82,
   "r": 18.76,
   "keys": [
    "conference-papers|20",
    "tech-reports|5",
    "tech-reports|6"
   ],
   "pale": true
  },
  {
   "id": "young-yun-baek",
   "name": "Young Yun Baek",
   "short": "Baek",
   "papers": 3,
   "inst": "University of Virginia",
   "color": "#86b6ef",
   "span": 2,
   "firstYear": 2020,
   "lastYear": 2022,
   "x": 206.96,
   "y": 151.17,
   "r": 18.76,
   "keys": [
    "journal-articles|21",
    "tech-reports|4",
    "tech-reports|7"
   ],
   "pale": true
  },
  {
   "id": "allison-codi",
   "name": "Allison Codi",
   "short": "Codi",
   "papers": 2,
   "inst": "Emory University",
   "color": "#5598e7",
   "span": 4,
   "firstYear": 2022,
   "lastYear": 2026,
   "x": -715.86,
   "y": -141.14,
   "r": 15.0,
   "keys": [
    "journal-articles|25",
    "journal-articles|44"
   ],
   "pale": true
  },
  {
   "id": "andrew-a-lover",
   "name": "Andrew A. Lover",
   "short": "Lover",
   "papers": 2,
   "inst": "University of Massachusetts Amherst",
   "color": "#5598e7",
   "span": 4,
   "firstYear": 2022,
   "lastYear": 2026,
   "x": -792.64,
   "y": -156.39,
   "r": 15.0,
   "keys": [
    "journal-articles|25",
    "journal-articles|44"
   ],
   "pale": true
  },
  {
   "id": "arash-haddadan",
   "name": "Arash Haddadan",
   "short": "Haddadan",
   "papers": 2,
   "inst": "University of Virginia",
   "color": "#86b6ef",
   "span": 1,
   "firstYear": 2021,
   "lastYear": 2022,
   "x": 417.58,
   "y": 232.61,
   "r": 15.0,
   "keys": [
    "conference-papers|28",
    "tech-reports|8"
   ],
   "pale": true
  },
  {
   "id": "aravind-srinivasan",
   "name": "Aravind Srinivasan",
   "short": "Srinivasan",
   "papers": 2,
   "inst": "University of Maryland, College Park",
   "color": "#86b6ef",
   "span": 1,
   "firstYear": 2021,
   "lastYear": 2022,
   "x": 372.59,
   "y": 235.73,
   "r": 15.0,
   "keys": [
    "conference-papers|28",
    "tech-reports|8"
   ],
   "pale": true
  },
  {
   "id": "arup-giri",
   "name": "Arup Giri",
   "short": "Giri",
   "papers": 2,
   "inst": "AVRDC - The World Vegetable Center",
   "color": "#86b6ef",
   "span": 2,
   "firstYear": 2017,
   "lastYear": 2019,
   "x": 474.13,
   "y": -208.7,
   "r": 15.0,
   "keys": [
    "conference-papers|12",
    "journal-articles|9"
   ],
   "pale": true
  },
  {
   "id": "bijaya-adhikari",
   "name": "Bijaya Adhikari",
   "short": "Adhikari",
   "papers": 2,
   "inst": "University of Iowa",
   "color": "#86b6ef",
   "span": 2,
   "firstYear": 2020,
   "lastYear": 2022,
   "x": -207.52,
   "y": -85.03,
   "r": 15.0,
   "keys": [
    "conference-papers|16",
    "journal-articles|24"
   ],
   "pale": true
  },
  {
   "id": "bowen-shi",
   "name": "Bowen Shi",
   "short": "Shi",
   "papers": 2,
   "inst": "Virginia Tech",
   "color": "#86b6ef",
   "span": 2,
   "firstYear": 2017,
   "lastYear": 2019,
   "x": 538.59,
   "y": -121.0,
   "r": 15.0,
   "keys": [
    "conference-papers|12",
    "journal-articles|9"
   ],
   "pale": true
  },
  {
   "id": "carrie-reed",
   "name": "Carrie Reed",
   "short": "Reed",
   "papers": 2,
   "inst": "Centers for Disease Control and Prevention",
   "color": "#86b6ef",
   "span": 0,
   "firstYear": 2023,
   "lastYear": 2023,
   "x": -577.11,
   "y": -123.79,
   "r": 15.0,
   "keys": [
    "journal-articles|28",
    "journal-articles|39"
   ],
   "pale": true
  },
  {
   "id": "erin-raymond",
   "name": "Erin Raymond",
   "short": "Raymond",
   "papers": 2,
   "inst": "University of Virginia",
   "color": "#86b6ef",
   "span": 0,
   "firstYear": 2020,
   "lastYear": 2020,
   "x": 373.89,
   "y": 0.63,
   "r": 15.0,
   "keys": [
    "conference-papers|18",
    "tech-reports|4"
   ],
   "pale": true
  },
  {
   "id": "farzaneh-sadat-tabataba",
   "name": "Farzaneh Sadat Tabataba",
   "short": "Tabataba",
   "papers": 2,
   "inst": "Virginia Tech",
   "color": "#86b6ef",
   "span": 0,
   "firstYear": 2017,
   "lastYear": 2017,
   "x": 239.94,
   "y": 119.92,
   "r": 15.0,
   "keys": [
    "conference-papers|11",
    "journal-articles|3"
   ],
   "pale": true
  },
  {
   "id": "gal-ehrlich",
   "name": "Gal Ehrlich",
   "short": "Ehrlich",
   "papers": 2,
   "inst": "Ehrlich & Fenster (Ehrlich Group)",
   "color": "#86b6ef",
   "span": 1,
   "firstYear": 2021,
   "lastYear": 2022,
   "x": 351.3,
   "y": 270.19,
   "r": 15.0,
   "keys": [
    "conference-papers|28",
    "tech-reports|8"
   ],
   "pale": true
  },
  {
   "id": "george-w-norton",
   "name": "George W. Norton",
   "short": "Norton",
   "papers": 2,
   "inst": "Virginia Tech",
   "color": "#86b6ef",
   "span": 2,
   "firstYear": 2017,
   "lastYear": 2019,
   "x": 518.36,
   "y": -197.42,
   "r": 15.0,
   "keys": [
    "conference-papers|12",
    "journal-articles|9"
   ],
   "pale": true
  },
  {
   "id": "ira-m-longini",
   "name": "Ira M. Longini",
   "short": "Longini",
   "papers": 2,
   "inst": "University of Florida",
   "color": "#86b6ef",
   "span": 0,
   "firstYear": 2023,
   "lastYear": 2023,
   "x": -125.66,
   "y": -108.39,
   "r": 15.0,
   "keys": [
    "journal-articles|28",
    "journal-articles|30"
   ],
   "pale": true
  },
  {
   "id": "k-s-nitin",
   "name": "K. S. Nitin",
   "short": "Nitin",
   "papers": 2,
   "inst": "Indian Institute of Horticultural Research",
   "color": "#86b6ef",
   "span": 2,
   "firstYear": 2017,
   "lastYear": 2019,
   "x": 441.38,
   "y": -181.44,
   "r": 15.0,
   "keys": [
    "conference-papers|12",
    "journal-articles|9"
   ],
   "pale": true
  },
  {
   "id": "lalit-prasad-sah",
   "name": "Lalit Prasad Sah",
   "short": "Sah",
   "papers": 2,
   "inst": "AVRDC - The World Vegetable Center",
   "color": "#86b6ef",
   "span": 2,
   "firstYear": 2017,
   "lastYear": 2019,
   "x": 485.28,
   "y": -171.01,
   "r": 15.0,
   "keys": [
    "conference-papers|12",
    "journal-articles|9"
   ],
   "pale": true
  },
  {
   "id": "luke-a-colavito",
   "name": "Luke A. Colavito",
   "short": "Colavito",
   "papers": 2,
   "inst": "AVRDC - The World Vegetable Center",
   "color": "#86b6ef",
   "span": 2,
   "firstYear": 2017,
   "lastYear": 2019,
   "x": 452.01,
   "y": -143.65,
   "r": 15.0,
   "keys": [
    "conference-papers|12",
    "journal-articles|9"
   ],
   "pale": true
  },
  {
   "id": "maier-fenster",
   "name": "Maier Fenster",
   "short": "Fenster",
   "papers": 2,
   "inst": "Ehrlich & Fenster (Ehrlich Group)",
   "color": "#86b6ef",
   "span": 1,
   "firstYear": 2021,
   "lastYear": 2022,
   "x": 312.48,
   "y": 249.85,
   "r": 15.0,
   "keys": [
    "conference-papers|28",
    "tech-reports|8"
   ],
   "pale": true
  },
  {
   "id": "maimuna-s-majumder",
   "name": "Maimuna S. Majumder",
   "short": "Majumder",
   "papers": 2,
   "inst": "Boston Children's Hospital",
   "color": "#5598e7",
   "span": 4,
   "firstYear": 2022,
   "lastYear": 2026,
   "x": -737.72,
   "y": -205.26,
   "r": 15.0,
   "keys": [
    "journal-articles|25",
    "journal-articles|44"
   ],
   "pale": true
  },
  {
   "id": "p-r-eastham",
   "name": "P. R. Eastham",
   "short": "Eastham",
   "papers": 2,
   "inst": "Google (United States)",
   "color": "#86b6ef",
   "span": 1,
   "firstYear": 2020,
   "lastYear": 2021,
   "x": 16.44,
   "y": 209.16,
   "r": 15.0,
   "keys": [
    "journal-articles|17",
    "tech-reports|6"
   ],
   "pale": true
  },
  {
   "id": "paolo-bocchini",
   "name": "Paolo Bocchini",
   "short": "Bocchini",
   "papers": 2,
   "inst": "Lehigh University",
   "color": "#5598e7",
   "span": 4,
   "firstYear": 2022,
   "lastYear": 2026,
   "x": -759.56,
   "y": -129.6,
   "r": 15.0,
   "keys": [
    "journal-articles|25",
    "journal-articles|44"
   ],
   "pale": true
  },
  {
   "id": "patrick-corbett",
   "name": "Patrick Corbett",
   "short": "Corbett",
   "papers": 2,
   "inst": "Virginia Department of Health",
   "color": "#86b6ef",
   "span": 1,
   "firstYear": 2020,
   "lastYear": 2021,
   "x": -158.26,
   "y": 5.81,
   "r": 15.0,
   "keys": [
    "journal-articles|10",
    "journal-articles|18"
   ],
   "pale": true
  },
  {
   "id": "pragati-prasad",
   "name": "Pragati Prasad",
   "short": "Prasad",
   "papers": 2,
   "inst": "Centers for Disease Control and Prevention",
   "color": "#86b6ef",
   "span": 1,
   "firstYear": 2023,
   "lastYear": 2024,
   "x": -148.88,
   "y": -141.96,
   "r": 15.0,
   "keys": [
    "journal-articles|28",
    "journal-articles|33"
   ],
   "pale": true
  },
  {
   "id": "prathyush-sambaturu",
   "name": "Prathyush Sambaturu",
   "short": "Sambaturu",
   "papers": 2,
   "inst": "University of Virginia",
   "color": "#86b6ef",
   "span": 0,
   "firstYear": 2020,
   "lastYear": 2020,
   "x": 537.11,
   "y": 99.11,
   "r": 15.0,
   "keys": [
    "conference-papers|16",
    "journal-articles|12"
   ],
   "pale": true
  },
  {
   "id": "r-asokan",
   "name": "R. Asokan",
   "short": "Asokan",
   "papers": 2,
   "inst": "Indian Institute of Horticultural Research",
   "color": "#86b6ef",
   "span": 2,
   "firstYear": 2017,
   "lastYear": 2019,
   "x": 528.96,
   "y": -159.44,
   "r": 15.0,
   "keys": [
    "conference-papers|12",
    "journal-articles|9"
   ],
   "pale": true
  },
  {
   "id": "sandeep-gupta",
   "name": "Sandeep Gupta",
   "short": "Gupta",
   "papers": 2,
   "inst": "University of Virginia",
   "color": "#86b6ef",
   "span": 2,
   "firstYear": 2017,
   "lastYear": 2019,
   "x": 281.45,
   "y": 105.07,
   "r": 15.0,
   "keys": [
    "conference-papers|10",
    "journal-articles|8"
   ],
   "pale": true
  },
  {
   "id": "shawn-t-brown",
   "name": "Shawn T. Brown",
   "short": "Brown",
   "papers": 2,
   "inst": "Hewlett-Packard (United States)",
   "color": "#6da7ec",
   "span": 3,
   "firstYear": 2021,
   "lastYear": 2024,
   "x": 327.15,
   "y": 169.83,
   "r": 15.0,
   "keys": [
    "conference-papers|25",
    "journal-articles|35"
   ],
   "pale": true
  },
  {
   "id": "sichao-wu",
   "name": "Sichao Wu",
   "short": "Wu",
   "papers": 2,
   "inst": "Virginia Tech",
   "color": "#86b6ef",
   "span": 2,
   "firstYear": 2017,
   "lastYear": 2019,
   "x": 463.61,
   "y": -105.43,
   "r": 15.0,
   "keys": [
    "conference-papers|12",
    "journal-articles|9"
   ],
   "pale": true
  },
  {
   "id": "sifat-afroj-moon",
   "name": "Sifat Afroj Moon",
   "short": "Moon",
   "papers": 2,
   "inst": "University of Virginia",
   "color": "#86b6ef",
   "span": 1,
   "firstYear": 2023,
   "lastYear": 2024,
   "x": 311.51,
   "y": 133.2,
   "r": 15.0,
   "keys": [
    "conference-papers|36",
    "journal-articles|29"
   ],
   "pale": true
  },
  {
   "id": "srikar-mutnuri",
   "name": "Srikar Mutnuri",
   "short": "Mutnuri",
   "papers": 2,
   "inst": "University of Virginia",
   "color": "#86b6ef",
   "span": 0,
   "firstYear": 2025,
   "lastYear": 2025,
   "x": 12.78,
   "y": 167.22,
   "r": 15.0,
   "keys": [
    "conference-papers|37",
    "conference-papers|40"
   ],
   "pale": true
  },
  {
   "id": "steven-riley",
   "name": "Steven Riley",
   "short": "Riley",
   "papers": 2,
   "inst": "Imperial College London",
   "color": "#86b6ef",
   "span": 1,
   "firstYear": 2021,
   "lastYear": 2022,
   "x": -228.84,
   "y": -123.54,
   "r": 15.0,
   "keys": [
    "journal-articles|19",
    "journal-articles|24"
   ],
   "pale": true
  },
  {
   "id": "sylvain-chevalier",
   "name": "Sylvain Chevalier",
   "short": "Chevalier",
   "papers": 2,
   "inst": "Metaculus",
   "color": "#5598e7",
   "span": 4,
   "firstYear": 2022,
   "lastYear": 2026,
   "x": -781.69,
   "y": -194.43,
   "r": 15.0,
   "keys": [
    "journal-articles|25",
    "journal-articles|44"
   ],
   "pale": true
  },
  {
   "id": "tamay-besiroglu",
   "name": "Tamay Besiroglu",
   "short": "Besiroglu",
   "papers": 2,
   "inst": "MIT Computer Science and Artificial Intelligence Laboratory",
   "color": "#5598e7",
   "span": 4,
   "firstYear": 2022,
   "lastYear": 2026,
   "x": -748.91,
   "y": -167.38,
   "r": 15.0,
   "keys": [
    "journal-articles|25",
    "journal-articles|44"
   ],
   "pale": true
  },
  {
   "id": "v-sridhar",
   "name": "V. Sridhar",
   "short": "Sridhar",
   "papers": 2,
   "inst": "Indian Institute of Horticultural Research",
   "color": "#86b6ef",
   "span": 2,
   "firstYear": 2017,
   "lastYear": 2019,
   "x": 495.81,
   "y": -132.98,
   "r": 15.0,
   "keys": [
    "conference-papers|12",
    "journal-articles|9"
   ],
   "pale": true
  },
  {
   "id": "willem-g-van-panhuis",
   "name": "Willem G. van Panhuis",
   "short": "Panhuis",
   "papers": 2,
   "inst": "National Institute of Allergy and Infectious Diseases",
   "color": "#86b6ef",
   "span": 2,
   "firstYear": 2021,
   "lastYear": 2023,
   "x": -162.03,
   "y": -84.75,
   "r": 15.0,
   "keys": [
    "journal-articles|19",
    "journal-articles|30"
   ],
   "pale": true
  },
  {
   "id": "xiaopeng-zhang",
   "name": "Xiaopeng Zhang",
   "short": "Zhang",
   "papers": 2,
   "inst": "Tencent (China)",
   "color": "#86b6ef",
   "span": 0,
   "firstYear": 2018,
   "lastYear": 2018,
   "x": -184.45,
   "y": -118.69,
   "r": 15.0,
   "keys": [
    "conference-papers|13",
    "journal-articles|6"
   ],
   "pale": true
  }
 ],
 "edges": [
  {
   "a": "madhav-marathe",
   "b": "bryan-lewis",
   "w": 46,
   "na": true,
   "nb": true
  },
  {
   "a": "madhav-marathe",
   "b": "jiangzhuo-chen",
   "w": 31,
   "na": true,
   "nb": true
  },
  {
   "a": "madhav-marathe",
   "b": "aniruddha-adiga",
   "w": 25,
   "na": true,
   "nb": true
  },
  {
   "a": "madhav-marathe",
   "b": "anil-vullikanti",
   "w": 20,
   "na": true,
   "nb": true
  },
  {
   "a": "madhav-marathe",
   "b": "henning-mortveit",
   "w": 21,
   "na": true,
   "nb": true
  },
  {
   "a": "madhav-marathe",
   "b": "przemyslaw-porebski",
   "w": 11,
   "na": false,
   "nb": true
  },
  {
   "a": "madhav-marathe",
   "b": "christopher-l-barrett",
   "w": 17,
   "na": false,
   "nb": true
  },
  {
   "a": "madhav-marathe",
   "b": "lijing-wang",
   "w": 11,
   "na": false,
   "nb": true
  },
  {
   "a": "madhav-marathe",
   "b": "stefan-hoops",
   "w": 12,
   "na": false,
   "nb": true
  },
  {
   "a": "madhav-marathe",
   "b": "benjamin-hurt",
   "w": 6,
   "na": false,
   "nb": true
  },
  {
   "a": "madhav-marathe",
   "b": "parantapa-bhattacharya",
   "w": 10,
   "na": false,
   "nb": true
  },
  {
   "a": "madhav-marathe",
   "b": "samarth-swarup",
   "w": 13,
   "na": false,
   "nb": true
  },
  {
   "a": "madhav-marathe",
   "b": "abhijin-adiga",
   "w": 10,
   "na": false,
   "nb": true
  },
  {
   "a": "madhav-marathe",
   "b": "dustin-machi",
   "w": 8,
   "na": false,
   "nb": true
  },
  {
   "a": "madhav-marathe",
   "b": "mandy-wilson",
   "w": 11,
   "na": false,
   "nb": true
  },
  {
   "a": "madhav-marathe",
   "b": "achla-marathe",
   "w": 10,
   "na": false,
   "nb": true
  },
  {
   "a": "madhav-marathe",
   "b": "brian-klahn",
   "w": 6,
   "na": false,
   "nb": true
  },
  {
   "a": "madhav-marathe",
   "b": "stephen-eubank",
   "w": 10,
   "na": false,
   "nb": true
  },
  {
   "a": "madhav-marathe",
   "b": "joseph-outten",
   "w": 4,
   "na": false,
   "nb": true
  },
  {
   "a": "madhav-marathe",
   "b": "harry-hochheiser",
   "w": 2,
   "na": false,
   "nb": true
  },
  {
   "a": "madhav-marathe",
   "b": "adam-sadilek",
   "w": 7,
   "na": false,
   "nb": true
  },
  {
   "a": "madhav-marathe",
   "b": "zakaria-mehrab",
   "w": 7,
   "na": false,
   "nb": true
  },
  {
   "a": "madhav-marathe",
   "b": "akhil-sai-peddireddy",
   "w": 3,
   "na": false,
   "nb": true
  },
  {
   "a": "madhav-marathe",
   "b": "andrew-warren",
   "w": 6,
   "na": false,
   "nb": true
  },
  {
   "a": "madhav-marathe",
   "b": "dawen-xie",
   "w": 6,
   "na": false,
   "nb": true
  },
  {
   "a": "madhav-marathe",
   "b": "gursharn-kaur",
   "w": 4,
   "na": false,
   "nb": true
  },
  {
   "a": "madhav-marathe",
   "b": "baltazar-espinoza",
   "w": 4,
   "na": false,
   "nb": true
  },
  {
   "a": "madhav-marathe",
   "b": "dave-higdon",
   "w": 5,
   "na": false,
   "nb": true
  },
  {
   "a": "madhav-marathe",
   "b": "david-leblang",
   "w": 5,
   "na": false,
   "nb": true
  },
  {
   "a": "madhav-marathe",
   "b": "rajesh-sundaresan",
   "w": 5,
   "na": false,
   "nb": true
  },
  {
   "a": "madhav-marathe",
   "b": "arindam-fadikar",
   "w": 4,
   "na": false,
   "nb": true
  },
  {
   "a": "madhav-marathe",
   "b": "justin-crow",
   "w": 4,
   "na": false,
   "nb": true
  },
  {
   "a": "madhav-marathe",
   "b": "siva-athreya",
   "w": 4,
   "na": false,
   "nb": true
  },
  {
   "a": "madhav-marathe",
   "b": "h-vincent-poor",
   "w": 3,
   "na": false,
   "nb": true
  },
  {
   "a": "madhav-marathe",
   "b": "nihesh-rathod",
   "w": 3,
   "na": false,
   "nb": true
  },
  {
   "a": "madhav-marathe",
   "b": "s-s-ravi",
   "w": 3,
   "na": false,
   "nb": true
  },
  {
   "a": "madhav-marathe",
   "b": "sarath-yasodharan",
   "w": 3,
   "na": false,
   "nb": true
  },
  {
   "a": "madhav-marathe",
   "b": "simon-a-levin",
   "w": 3,
   "na": false,
   "nb": true
  },
  {
   "a": "madhav-marathe",
   "b": "xue-ben",
   "w": 3,
   "na": false,
   "nb": true
  },
  {
   "a": "madhav-marathe",
   "b": "young-yun-baek",
   "w": 3,
   "na": false,
   "nb": true
  },
  {
   "a": "madhav-marathe",
   "b": "farzaneh-sadat-tabataba",
   "w": 2,
   "na": false,
   "nb": true
  },
  {
   "a": "madhav-marathe",
   "b": "p-r-eastham",
   "w": 2,
   "na": false,
   "nb": true
  },
  {
   "a": "madhav-marathe",
   "b": "sandeep-gupta",
   "w": 2,
   "na": false,
   "nb": true
  },
  {
   "a": "madhav-marathe",
   "b": "srikar-mutnuri",
   "w": 2,
   "na": false,
   "nb": true
  },
  {
   "a": "bryan-lewis",
   "b": "jiangzhuo-chen",
   "w": 29,
   "na": true,
   "nb": true
  },
  {
   "a": "bryan-lewis",
   "b": "aniruddha-adiga",
   "w": 18,
   "na": true,
   "nb": true
  },
  {
   "a": "bryan-lewis",
   "b": "anil-vullikanti",
   "w": 19,
   "na": true,
   "nb": true
  },
  {
   "a": "bryan-lewis",
   "b": "henning-mortveit",
   "w": 20,
   "na": true,
   "nb": true
  },
  {
   "a": "bryan-lewis",
   "b": "przemyslaw-porebski",
   "w": 10,
   "na": false,
   "nb": true
  },
  {
   "a": "bryan-lewis",
   "b": "christopher-l-barrett",
   "w": 17,
   "na": false,
   "nb": true
  },
  {
   "a": "bryan-lewis",
   "b": "lijing-wang",
   "w": 10,
   "na": false,
   "nb": true
  },
  {
   "a": "bryan-lewis",
   "b": "stefan-hoops",
   "w": 12,
   "na": false,
   "nb": true
  },
  {
   "a": "bryan-lewis",
   "b": "benjamin-hurt",
   "w": 6,
   "na": false,
   "nb": true
  },
  {
   "a": "bryan-lewis",
   "b": "parantapa-bhattacharya",
   "w": 9,
   "na": false,
   "nb": true
  },
  {
   "a": "bryan-lewis",
   "b": "samarth-swarup",
   "w": 11,
   "na": false,
   "nb": true
  },
  {
   "a": "bryan-lewis",
   "b": "mandy-wilson",
   "w": 11,
   "na": false,
   "nb": true
  },
  {
   "a": "bryan-lewis",
   "b": "stephen-eubank",
   "w": 8,
   "na": false,
   "nb": true
  },
  {
   "a": "bryan-lewis",
   "b": "joseph-outten",
   "w": 4,
   "na": false,
   "nb": true
  },
  {
   "a": "bryan-lewis",
   "b": "harry-hochheiser",
   "w": 2,
   "na": false,
   "nb": true
  },
  {
   "a": "bryan-lewis",
   "b": "adam-sadilek",
   "w": 4,
   "na": false,
   "nb": true
  },
  {
   "a": "bryan-lewis",
   "b": "zakaria-mehrab",
   "w": 5,
   "na": false,
   "nb": true
  },
  {
   "a": "bryan-lewis",
   "b": "andrew-warren",
   "w": 6,
   "na": false,
   "nb": true
  },
  {
   "a": "bryan-lewis",
   "b": "gursharn-kaur",
   "w": 4,
   "na": false,
   "nb": true
  },
  {
   "a": "bryan-lewis",
   "b": "baltazar-espinoza",
   "w": 4,
   "na": false,
   "nb": true
  },
  {
   "a": "bryan-lewis",
   "b": "dave-higdon",
   "w": 5,
   "na": false,
   "nb": true
  },
  {
   "a": "bryan-lewis",
   "b": "david-leblang",
   "w": 5,
   "na": false,
   "nb": true
  },
  {
   "a": "bryan-lewis",
   "b": "arindam-fadikar",
   "w": 4,
   "na": false,
   "nb": true
  },
  {
   "a": "bryan-lewis",
   "b": "justin-crow",
   "w": 4,
   "na": false,
   "nb": true
  },
  {
   "a": "bryan-lewis",
   "b": "logan-stundal",
   "w": 4,
   "na": false,
   "nb": true
  },
  {
   "a": "bryan-lewis",
   "b": "h-vincent-poor",
   "w": 3,
   "na": false,
   "nb": true
  },
  {
   "a": "bryan-lewis",
   "b": "james-schlitt",
   "w": 2,
   "na": false,
   "nb": true
  },
  {
   "a": "bryan-lewis",
   "b": "mark-orr",
   "w": 3,
   "na": false,
   "nb": true
  },
  {
   "a": "bryan-lewis",
   "b": "pyrros-a-telionis",
   "w": 2,
   "na": false,
   "nb": true
  },
  {
   "a": "bryan-lewis",
   "b": "s-s-ravi",
   "w": 3,
   "na": false,
   "nb": true
  },
  {
   "a": "bryan-lewis",
   "b": "simon-a-levin",
   "w": 3,
   "na": false,
   "nb": true
  },
  {
   "a": "bryan-lewis",
   "b": "farzaneh-sadat-tabataba",
   "w": 2,
   "na": false,
   "nb": true
  },
  {
   "a": "bryan-lewis",
   "b": "sandeep-gupta",
   "w": 2,
   "na": false,
   "nb": true
  },
  {
   "a": "bryan-lewis",
   "b": "sifat-afroj-moon",
   "w": 2,
   "na": false,
   "nb": true
  },
  {
   "a": "jiangzhuo-chen",
   "b": "aniruddha-adiga",
   "w": 12,
   "na": false,
   "nb": true
  },
  {
   "a": "jiangzhuo-chen",
   "b": "anil-vullikanti",
   "w": 18,
   "na": true,
   "nb": true
  },
  {
   "a": "jiangzhuo-chen",
   "b": "henning-mortveit",
   "w": 16,
   "na": true,
   "nb": true
  },
  {
   "a": "jiangzhuo-chen",
   "b": "christopher-l-barrett",
   "w": 13,
   "na": true,
   "nb": true
  },
  {
   "a": "jiangzhuo-chen",
   "b": "lijing-wang",
   "w": 8,
   "na": false,
   "nb": true
  },
  {
   "a": "jiangzhuo-chen",
   "b": "stefan-hoops",
   "w": 12,
   "na": false,
   "nb": true
  },
  {
   "a": "jiangzhuo-chen",
   "b": "parantapa-bhattacharya",
   "w": 9,
   "na": false,
   "nb": true
  },
  {
   "a": "jiangzhuo-chen",
   "b": "abhijin-adiga",
   "w": 7,
   "na": false,
   "nb": true
  },
  {
   "a": "jiangzhuo-chen",
   "b": "mandy-wilson",
   "w": 11,
   "na": false,
   "nb": true
  },
  {
   "a": "jiangzhuo-chen",
   "b": "achla-marathe",
   "w": 8,
   "na": false,
   "nb": true
  },
  {
   "a": "jiangzhuo-chen",
   "b": "stephen-eubank",
   "w": 7,
   "na": false,
   "nb": true
  },
  {
   "a": "jiangzhuo-chen",
   "b": "joseph-outten",
   "w": 4,
   "na": false,
   "nb": true
  },
  {
   "a": "jiangzhuo-chen",
   "b": "adam-sadilek",
   "w": 6,
   "na": false,
   "nb": true
  },
  {
   "a": "jiangzhuo-chen",
   "b": "andrew-warren",
   "w": 4,
   "na": false,
   "nb": true
  },
  {
   "a": "jiangzhuo-chen",
   "b": "dave-higdon",
   "w": 5,
   "na": false,
   "nb": true
  },
  {
   "a": "jiangzhuo-chen",
   "b": "arindam-fadikar",
   "w": 4,
   "na": false,
   "nb": true
  },
  {
   "a": "jiangzhuo-chen",
   "b": "james-schlitt",
   "w": 2,
   "na": false,
   "nb": true
  },
  {
   "a": "jiangzhuo-chen",
   "b": "wen-you",
   "w": 3,
   "na": false,
   "nb": true
  },
  {
   "a": "jiangzhuo-chen",
   "b": "farzaneh-sadat-tabataba",
   "w": 2,
   "na": false,
   "nb": true
  },
  {
   "a": "jiangzhuo-chen",
   "b": "sandeep-gupta",
   "w": 2,
   "na": false,
   "nb": true
  },
  {
   "a": "jiangzhuo-chen",
   "b": "sifat-afroj-moon",
   "w": 2,
   "na": false,
   "nb": true
  },
  {
   "a": "aniruddha-adiga",
   "b": "przemyslaw-porebski",
   "w": 8,
   "na": true,
   "nb": true
  },
  {
   "a": "aniruddha-adiga",
   "b": "lijing-wang",
   "w": 10,
   "na": true,
   "nb": true
  },
  {
   "a": "aniruddha-adiga",
   "b": "benjamin-hurt",
   "w": 6,
   "na": false,
   "nb": true
  },
  {
   "a": "aniruddha-adiga",
   "b": "samarth-swarup",
   "w": 6,
   "na": false,
   "nb": true
  },
  {
   "a": "aniruddha-adiga",
   "b": "adam-sadilek",
   "w": 5,
   "na": false,
   "nb": true
  },
  {
   "a": "aniruddha-adiga",
   "b": "andrew-warren",
   "w": 4,
   "na": false,
   "nb": true
  },
  {
   "a": "aniruddha-adiga",
   "b": "gursharn-kaur",
   "w": 4,
   "na": false,
   "nb": true
  },
  {
   "a": "aniruddha-adiga",
   "b": "rajesh-sundaresan",
   "w": 5,
   "na": false,
   "nb": true
  },
  {
   "a": "aniruddha-adiga",
   "b": "justin-crow",
   "w": 2,
   "na": false,
   "nb": true
  },
  {
   "a": "aniruddha-adiga",
   "b": "siva-athreya",
   "w": 4,
   "na": false,
   "nb": true
  },
  {
   "a": "aniruddha-adiga",
   "b": "nihesh-rathod",
   "w": 3,
   "na": false,
   "nb": true
  },
  {
   "a": "aniruddha-adiga",
   "b": "sarath-yasodharan",
   "w": 3,
   "na": false,
   "nb": true
  },
  {
   "a": "aniruddha-adiga",
   "b": "srikar-mutnuri",
   "w": 2,
   "na": false,
   "nb": true
  },
  {
   "a": "anil-vullikanti",
   "b": "henning-mortveit",
   "w": 10,
   "na": true,
   "nb": false
  },
  {
   "a": "anil-vullikanti",
   "b": "christopher-l-barrett",
   "w": 9,
   "na": true,
   "nb": false
  },
  {
   "a": "anil-vullikanti",
   "b": "joseph-outten",
   "w": 4,
   "na": false,
   "nb": true
  },
  {
   "a": "anil-vullikanti",
   "b": "baltazar-espinoza",
   "w": 3,
   "na": false,
   "nb": true
  },
  {
   "a": "anil-vullikanti",
   "b": "dave-higdon",
   "w": 3,
   "na": false,
   "nb": true
  },
  {
   "a": "anil-vullikanti",
   "b": "prathyush-sambaturu",
   "w": 2,
   "na": false,
   "nb": true
  },
  {
   "a": "anil-vullikanti",
   "b": "sandeep-gupta",
   "w": 2,
   "na": false,
   "nb": true
  },
  {
   "a": "anil-vullikanti",
   "b": "sifat-afroj-moon",
   "w": 2,
   "na": false,
   "nb": true
  },
  {
   "a": "henning-mortveit",
   "b": "christopher-l-barrett",
   "w": 13,
   "na": true,
   "nb": true
  },
  {
   "a": "henning-mortveit",
   "b": "stefan-hoops",
   "w": 12,
   "na": true,
   "nb": true
  },
  {
   "a": "henning-mortveit",
   "b": "samarth-swarup",
   "w": 7,
   "na": false,
   "nb": true
  },
  {
   "a": "henning-mortveit",
   "b": "abhijin-adiga",
   "w": 7,
   "na": false,
   "nb": true
  },
  {
   "a": "henning-mortveit",
   "b": "dustin-machi",
   "w": 7,
   "na": false,
   "nb": true
  },
  {
   "a": "henning-mortveit",
   "b": "zakaria-mehrab",
   "w": 5,
   "na": false,
   "nb": true
  },
  {
   "a": "henning-mortveit",
   "b": "david-leblang",
   "w": 5,
   "na": false,
   "nb": true
  },
  {
   "a": "henning-mortveit",
   "b": "justin-crow",
   "w": 2,
   "na": false,
   "nb": true
  },
  {
   "a": "henning-mortveit",
   "b": "logan-stundal",
   "w": 4,
   "na": false,
   "nb": true
  },
  {
   "a": "henning-mortveit",
   "b": "sandeep-gupta",
   "w": 2,
   "na": false,
   "nb": true
  },
  {
   "a": "przemyslaw-porebski",
   "b": "benjamin-hurt",
   "w": 6,
   "na": false,
   "nb": true
  },
  {
   "a": "przemyslaw-porebski",
   "b": "mandy-wilson",
   "w": 6,
   "na": true,
   "nb": false
  },
  {
   "a": "przemyslaw-porebski",
   "b": "brian-klahn",
   "w": 6,
   "na": true,
   "nb": true
  },
  {
   "a": "przemyslaw-porebski",
   "b": "akhil-sai-peddireddy",
   "w": 3,
   "na": false,
   "nb": true
  },
  {
   "a": "przemyslaw-porebski",
   "b": "gursharn-kaur",
   "w": 3,
   "na": false,
   "nb": true
  },
  {
   "a": "christopher-l-barrett",
   "b": "stefan-hoops",
   "w": 11,
   "na": true,
   "nb": true
  },
  {
   "a": "christopher-l-barrett",
   "b": "mandy-wilson",
   "w": 9,
   "na": false,
   "nb": true
  },
  {
   "a": "christopher-l-barrett",
   "b": "stephen-eubank",
   "w": 7,
   "na": false,
   "nb": true
  },
  {
   "a": "christopher-l-barrett",
   "b": "arindam-fadikar",
   "w": 2,
   "na": false,
   "nb": true
  },
  {
   "a": "christopher-l-barrett",
   "b": "justin-crow",
   "w": 2,
   "na": false,
   "nb": true
  },
  {
   "a": "christopher-l-barrett",
   "b": "mark-orr",
   "w": 2,
   "na": false,
   "nb": true
  },
  {
   "a": "christopher-l-barrett",
   "b": "wen-you",
   "w": 2,
   "na": false,
   "nb": true
  },
  {
   "a": "lijing-wang",
   "b": "adam-sadilek",
   "w": 6,
   "na": true,
   "nb": true
  },
  {
   "a": "lijing-wang",
   "b": "alok-talekar",
   "w": 3,
   "na": false,
   "nb": true
  },
  {
   "a": "lijing-wang",
   "b": "ashish-v-tendulkar",
   "w": 3,
   "na": false,
   "nb": true
  },
  {
   "a": "lijing-wang",
   "b": "gaurav-aggarwal",
   "w": 3,
   "na": false,
   "nb": true
  },
  {
   "a": "lijing-wang",
   "b": "milind-tambe",
   "w": 3,
   "na": false,
   "nb": true
  },
  {
   "a": "stefan-hoops",
   "b": "parantapa-bhattacharya",
   "w": 8,
   "na": false,
   "nb": true
  },
  {
   "a": "stefan-hoops",
   "b": "abhijin-adiga",
   "w": 7,
   "na": false,
   "nb": true
  },
  {
   "a": "stefan-hoops",
   "b": "dustin-machi",
   "w": 7,
   "na": false,
   "nb": true
  },
  {
   "a": "stefan-hoops",
   "b": "mandy-wilson",
   "w": 9,
   "na": false,
   "nb": true
  },
  {
   "a": "stefan-hoops",
   "b": "achla-marathe",
   "w": 7,
   "na": false,
   "nb": true
  },
  {
   "a": "stefan-hoops",
   "b": "dawen-xie",
   "w": 5,
   "na": false,
   "nb": true
  },
  {
   "a": "stefan-hoops",
   "b": "wen-you",
   "w": 2,
   "na": false,
   "nb": true
  },
  {
   "a": "benjamin-hurt",
   "b": "gursharn-kaur",
   "w": 3,
   "na": true,
   "nb": true
  },
  {
   "a": "parantapa-bhattacharya",
   "b": "dustin-machi",
   "w": 7,
   "na": false,
   "nb": true
  },
  {
   "a": "parantapa-bhattacharya",
   "b": "mandy-wilson",
   "w": 8,
   "na": true,
   "nb": false
  },
  {
   "a": "samarth-swarup",
   "b": "zakaria-mehrab",
   "w": 7,
   "na": true,
   "nb": true
  },
  {
   "a": "samarth-swarup",
   "b": "david-leblang",
   "w": 5,
   "na": false,
   "nb": true
  },
  {
   "a": "samarth-swarup",
   "b": "logan-stundal",
   "w": 4,
   "na": false,
   "nb": true
  },
  {
   "a": "samarth-swarup",
   "b": "s-s-ravi",
   "w": 2,
   "na": false,
   "nb": true
  },
  {
   "a": "shaun-truelove",
   "b": "c-cile-viboud",
   "w": 6,
   "na": true,
   "nb": true
  },
  {
   "a": "shaun-truelove",
   "b": "justin-lessler",
   "w": 4,
   "na": true,
   "nb": true
  },
  {
   "a": "shaun-truelove",
   "b": "harry-hochheiser",
   "w": 2,
   "na": true,
   "nb": true
  },
  {
   "a": "shaun-truelove",
   "b": "michael-c-runge",
   "w": 2,
   "na": true,
   "nb": true
  },
  {
   "a": "shaun-truelove",
   "b": "sara-l-loo",
   "w": 3,
   "na": true,
   "nb": true
  },
  {
   "a": "abhijin-adiga",
   "b": "achla-marathe",
   "w": 8,
   "na": true,
   "nb": true
  },
  {
   "a": "abhijin-adiga",
   "b": "r-muniappan",
   "w": 3,
   "na": false,
   "nb": true
  },
  {
   "a": "alessandro-vespignani",
   "b": "matthew-biggerstaff",
   "w": 2,
   "na": true,
   "nb": true
  },
  {
   "a": "alessandro-vespignani",
   "b": "sasikiran-kandula",
   "w": 2,
   "na": true,
   "nb": true
  },
  {
   "a": "dustin-machi",
   "b": "mandy-wilson",
   "w": 7,
   "na": true,
   "nb": false
  },
  {
   "a": "dustin-machi",
   "b": "brian-klahn",
   "w": 5,
   "na": false,
   "nb": true
  },
  {
   "a": "dustin-machi",
   "b": "dawen-xie",
   "w": 5,
   "na": false,
   "nb": true
  },
  {
   "a": "dustin-machi",
   "b": "erin-raymond",
   "w": 2,
   "na": false,
   "nb": true
  },
  {
   "a": "mandy-wilson",
   "b": "brian-klahn",
   "w": 6,
   "na": false,
   "nb": true
  },
  {
   "a": "mandy-wilson",
   "b": "dawen-xie",
   "w": 6,
   "na": false,
   "nb": true
  },
  {
   "a": "mandy-wilson",
   "b": "james-schlitt",
   "w": 2,
   "na": false,
   "nb": true
  },
  {
   "a": "mandy-wilson",
   "b": "mark-orr",
   "w": 2,
   "na": false,
   "nb": true
  },
  {
   "a": "mandy-wilson",
   "b": "erin-raymond",
   "w": 2,
   "na": false,
   "nb": true
  },
  {
   "a": "mandy-wilson",
   "b": "shawn-t-brown",
   "w": 2,
   "na": false,
   "nb": true
  },
  {
   "a": "achla-marathe",
   "b": "stephen-eubank",
   "w": 8,
   "na": true,
   "nb": true
  },
  {
   "a": "achla-marathe",
   "b": "wen-you",
   "w": 3,
   "na": false,
   "nb": true
  },
  {
   "a": "achla-marathe",
   "b": "arash-haddadan",
   "w": 2,
   "na": false,
   "nb": true
  },
  {
   "a": "achla-marathe",
   "b": "aravind-srinivasan",
   "w": 2,
   "na": false,
   "nb": true
  },
  {
   "a": "achla-marathe",
   "b": "gal-ehrlich",
   "w": 2,
   "na": false,
   "nb": true
  },
  {
   "a": "achla-marathe",
   "b": "maier-fenster",
   "w": 2,
   "na": false,
   "nb": true
  },
  {
   "a": "achla-marathe",
   "b": "shawn-t-brown",
   "w": 2,
   "na": false,
   "nb": true
  },
  {
   "a": "brian-klahn",
   "b": "akhil-sai-peddireddy",
   "w": 2,
   "na": false,
   "nb": true
  },
  {
   "a": "brian-klahn",
   "b": "dawen-xie",
   "w": 5,
   "na": true,
   "nb": true
  },
  {
   "a": "brian-klahn",
   "b": "young-yun-baek",
   "w": 2,
   "na": false,
   "nb": true
  },
  {
   "a": "brian-klahn",
   "b": "erin-raymond",
   "w": 2,
   "na": false,
   "nb": true
  },
  {
   "a": "brian-klahn",
   "b": "shawn-t-brown",
   "w": 2,
   "na": false,
   "nb": true
  },
  {
   "a": "c-cile-viboud",
   "b": "justin-lessler",
   "w": 7,
   "na": true,
   "nb": true
  },
  {
   "a": "c-cile-viboud",
   "b": "emily-howerton",
   "w": 5,
   "na": true,
   "nb": true
  },
  {
   "a": "c-cile-viboud",
   "b": "katriona-shea",
   "w": 3,
   "na": false,
   "nb": true
  },
  {
   "a": "c-cile-viboud",
   "b": "michael-a-johansson",
   "w": 3,
   "na": false,
   "nb": true
  },
  {
   "a": "c-cile-viboud",
   "b": "michael-c-runge",
   "w": 3,
   "na": false,
   "nb": true
  },
  {
   "a": "c-cile-viboud",
   "b": "rebecca-k-borchering",
   "w": 3,
   "na": true,
   "nb": true
  },
  {
   "a": "c-cile-viboud",
   "b": "sara-l-loo",
   "w": 3,
   "na": true,
   "nb": true
  },
  {
   "a": "justin-lessler",
   "b": "emily-howerton",
   "w": 5,
   "na": true,
   "nb": true
  },
  {
   "a": "justin-lessler",
   "b": "katriona-shea",
   "w": 3,
   "na": true,
   "nb": true
  },
  {
   "a": "justin-lessler",
   "b": "michael-c-runge",
   "w": 2,
   "na": false,
   "nb": true
  },
  {
   "a": "justin-lessler",
   "b": "rebecca-k-borchering",
   "w": 3,
   "na": true,
   "nb": true
  },
  {
   "a": "justin-lessler",
   "b": "sara-l-loo",
   "w": 2,
   "na": false,
   "nb": true
  },
  {
   "a": "stephen-eubank",
   "b": "james-schlitt",
   "w": 2,
   "na": false,
   "nb": true
  },
  {
   "a": "stephen-eubank",
   "b": "mark-orr",
   "w": 2,
   "na": false,
   "nb": true
  },
  {
   "a": "stephen-eubank",
   "b": "wen-you",
   "w": 2,
   "na": false,
   "nb": true
  },
  {
   "a": "stephen-eubank",
   "b": "young-yun-baek",
   "w": 2,
   "na": false,
   "nb": true
  },
  {
   "a": "stephen-eubank",
   "b": "arash-haddadan",
   "w": 2,
   "na": false,
   "nb": true
  },
  {
   "a": "stephen-eubank",
   "b": "aravind-srinivasan",
   "w": 2,
   "na": false,
   "nb": true
  },
  {
   "a": "stephen-eubank",
   "b": "gal-ehrlich",
   "w": 2,
   "na": false,
   "nb": true
  },
  {
   "a": "stephen-eubank",
   "b": "maier-fenster",
   "w": 2,
   "na": false,
   "nb": true
  },
  {
   "a": "matthew-biggerstaff",
   "b": "nicholas-g-reich",
   "w": 2,
   "na": true,
   "nb": true
  },
  {
   "a": "matthew-biggerstaff",
   "b": "michael-a-johansson",
   "w": 3,
   "na": true,
   "nb": true
  },
  {
   "a": "matthew-biggerstaff",
   "b": "sasikiran-kandula",
   "w": 2,
   "na": true,
   "nb": true
  },
  {
   "a": "matthew-biggerstaff",
   "b": "carrie-reed",
   "w": 2,
   "na": true,
   "nb": true
  },
  {
   "a": "joseph-outten",
   "b": "dawen-xie",
   "w": 3,
   "na": true,
   "nb": false
  },
  {
   "a": "joseph-outten",
   "b": "shawn-t-brown",
   "w": 2,
   "na": false,
   "nb": true
  },
  {
   "a": "emily-howerton",
   "b": "katriona-shea",
   "w": 3,
   "na": true,
   "nb": true
  },
  {
   "a": "emily-howerton",
   "b": "michael-c-runge",
   "w": 2,
   "na": true,
   "nb": true
  },
  {
   "a": "emily-howerton",
   "b": "rebecca-k-borchering",
   "w": 3,
   "na": true,
   "nb": true
  },
  {
   "a": "katriona-shea",
   "b": "rebecca-k-borchering",
   "w": 2,
   "na": true,
   "nb": true
  },
  {
   "a": "nicholas-g-reich",
   "b": "michael-a-johansson",
   "w": 2,
   "na": true,
   "nb": true
  },
  {
   "a": "adam-sadilek",
   "b": "alok-talekar",
   "w": 3,
   "na": false,
   "nb": true
  },
  {
   "a": "adam-sadilek",
   "b": "ashish-v-tendulkar",
   "w": 3,
   "na": false,
   "nb": true
  },
  {
   "a": "adam-sadilek",
   "b": "gaurav-aggarwal",
   "w": 3,
   "na": false,
   "nb": true
  },
  {
   "a": "adam-sadilek",
   "b": "milind-tambe",
   "w": 3,
   "na": false,
   "nb": true
  },
  {
   "a": "adam-sadilek",
   "b": "xue-ben",
   "w": 3,
   "na": false,
   "nb": true
  },
  {
   "a": "adam-sadilek",
   "b": "p-r-eastham",
   "w": 2,
   "na": false,
   "nb": true
  },
  {
   "a": "dah-ming-chiu",
   "b": "yan-wu",
   "w": 4,
   "na": true,
   "nb": true
  },
  {
   "a": "dah-ming-chiu",
   "b": "qiu-fang-ying",
   "w": 3,
   "na": true,
   "nb": true
  },
  {
   "a": "dah-ming-chiu",
   "b": "xiaopeng-zhang",
   "w": 2,
   "na": true,
   "nb": true
  },
  {
   "a": "michael-c-runge",
   "b": "rebecca-k-borchering",
   "w": 2,
   "na": true,
   "nb": true
  },
  {
   "a": "zakaria-mehrab",
   "b": "david-leblang",
   "w": 5,
   "na": true,
   "nb": true
  },
  {
   "a": "zakaria-mehrab",
   "b": "logan-stundal",
   "w": 4,
   "na": false,
   "nb": true
  },
  {
   "a": "zakaria-mehrab",
   "b": "s-s-ravi",
   "w": 2,
   "na": false,
   "nb": true
  },
  {
   "a": "akhil-sai-peddireddy",
   "b": "dawen-xie",
   "w": 2,
   "na": true,
   "nb": false
  },
  {
   "a": "akhil-sai-peddireddy",
   "b": "erin-raymond",
   "w": 2,
   "na": true,
   "nb": true
  },
  {
   "a": "andrew-warren",
   "b": "baltazar-espinoza",
   "w": 4,
   "na": true,
   "nb": true
  },
  {
   "a": "andrew-warren",
   "b": "h-vincent-poor",
   "w": 2,
   "na": false,
   "nb": true
  },
  {
   "a": "andrew-warren",
   "b": "simon-a-levin",
   "w": 2,
   "na": false,
   "nb": true
  },
  {
   "a": "andrew-warren",
   "b": "young-yun-baek",
   "w": 2,
   "na": false,
   "nb": true
  },
  {
   "a": "andrew-warren",
   "b": "sifat-afroj-moon",
   "w": 2,
   "na": false,
   "nb": true
  },
  {
   "a": "dawen-xie",
   "b": "young-yun-baek",
   "w": 2,
   "na": false,
   "nb": true
  },
  {
   "a": "dawen-xie",
   "b": "erin-raymond",
   "w": 2,
   "na": false,
   "nb": true
  },
  {
   "a": "dawen-xie",
   "b": "shawn-t-brown",
   "w": 2,
   "na": false,
   "nb": true
  },
  {
   "a": "baltazar-espinoza",
   "b": "h-vincent-poor",
   "w": 2,
   "na": false,
   "nb": true
  },
  {
   "a": "baltazar-espinoza",
   "b": "simon-a-levin",
   "w": 2,
   "na": false,
   "nb": true
  },
  {
   "a": "baltazar-espinoza",
   "b": "sifat-afroj-moon",
   "w": 2,
   "na": true,
   "nb": true
  },
  {
   "a": "dave-higdon",
   "b": "arindam-fadikar",
   "w": 3,
   "na": true,
   "nb": true
  },
  {
   "a": "david-leblang",
   "b": "logan-stundal",
   "w": 4,
   "na": false,
   "nb": true
  },
  {
   "a": "david-leblang",
   "b": "s-s-ravi",
   "w": 2,
   "na": false,
   "nb": true
  },
  {
   "a": "nikos-i-bosse",
   "b": "andrew-a-lover",
   "w": 2,
   "na": true,
   "nb": false
  },
  {
   "a": "nikos-i-bosse",
   "b": "maimuna-s-majumder",
   "w": 2,
   "na": true,
   "nb": false
  },
  {
   "a": "nikos-i-bosse",
   "b": "paolo-bocchini",
   "w": 2,
   "na": true,
   "nb": false
  },
  {
   "a": "nikos-i-bosse",
   "b": "sylvain-chevalier",
   "w": 2,
   "na": true,
   "nb": false
  },
  {
   "a": "nikos-i-bosse",
   "b": "tamay-besiroglu",
   "w": 2,
   "na": true,
   "nb": false
  },
  {
   "a": "rajesh-sundaresan",
   "b": "siva-athreya",
   "w": 4,
   "na": true,
   "nb": true
  },
  {
   "a": "rajesh-sundaresan",
   "b": "nihesh-rathod",
   "w": 3,
   "na": true,
   "nb": true
  },
  {
   "a": "rajesh-sundaresan",
   "b": "sarath-yasodharan",
   "w": 3,
   "na": true,
   "nb": true
  },
  {
   "a": "logan-stundal",
   "b": "abhishek-pandey",
   "w": 3,
   "na": false,
   "nb": true
  },
  {
   "a": "logan-stundal",
   "b": "alison-p-galvani",
   "w": 3,
   "na": false,
   "nb": true
  },
  {
   "a": "logan-stundal",
   "b": "burton-h-singer",
   "w": 3,
   "na": false,
   "nb": true
  },
  {
   "a": "logan-stundal",
   "b": "chad-r-wells",
   "w": 3,
   "na": false,
   "nb": true
  },
  {
   "a": "logan-stundal",
   "b": "rita-r-colwell",
   "w": 3,
   "na": false,
   "nb": true
  },
  {
   "a": "sam-abbott",
   "b": "andrew-a-lover",
   "w": 2,
   "na": true,
   "nb": false
  },
  {
   "a": "sam-abbott",
   "b": "maimuna-s-majumder",
   "w": 2,
   "na": true,
   "nb": false
  },
  {
   "a": "sam-abbott",
   "b": "paolo-bocchini",
   "w": 2,
   "na": true,
   "nb": false
  },
  {
   "a": "sam-abbott",
   "b": "sylvain-chevalier",
   "w": 2,
   "na": true,
   "nb": false
  },
  {
   "a": "sam-abbott",
   "b": "tamay-besiroglu",
   "w": 2,
   "na": true,
   "nb": false
  },
  {
   "a": "siva-athreya",
   "b": "nihesh-rathod",
   "w": 3,
   "na": true,
   "nb": true
  },
  {
   "a": "siva-athreya",
   "b": "sarath-yasodharan",
   "w": 3,
   "na": true,
   "nb": true
  },
  {
   "a": "thomas-mcandrew",
   "b": "andrew-a-lover",
   "w": 2,
   "na": true,
   "nb": false
  },
  {
   "a": "thomas-mcandrew",
   "b": "maimuna-s-majumder",
   "w": 2,
   "na": true,
   "nb": false
  },
  {
   "a": "thomas-mcandrew",
   "b": "paolo-bocchini",
   "w": 2,
   "na": true,
   "nb": false
  },
  {
   "a": "thomas-mcandrew",
   "b": "sylvain-chevalier",
   "w": 2,
   "na": true,
   "nb": false
  },
  {
   "a": "thomas-mcandrew",
   "b": "tamay-besiroglu",
   "w": 2,
   "na": true,
   "nb": false
  },
  {
   "a": "abhishek-pandey",
   "b": "alison-p-galvani",
   "w": 3,
   "na": true,
   "nb": true
  },
  {
   "a": "abhishek-pandey",
   "b": "burton-h-singer",
   "w": 3,
   "na": true,
   "nb": true
  },
  {
   "a": "abhishek-pandey",
   "b": "chad-r-wells",
   "w": 3,
   "na": true,
   "nb": true
  },
  {
   "a": "abhishek-pandey",
   "b": "rita-r-colwell",
   "w": 3,
   "na": true,
   "nb": true
  },
  {
   "a": "alison-p-galvani",
   "b": "burton-h-singer",
   "w": 3,
   "na": true,
   "nb": true
  },
  {
   "a": "alison-p-galvani",
   "b": "chad-r-wells",
   "w": 3,
   "na": true,
   "nb": true
  },
  {
   "a": "alison-p-galvani",
   "b": "rita-r-colwell",
   "w": 3,
   "na": true,
   "nb": true
  },
  {
   "a": "alok-talekar",
   "b": "ashish-v-tendulkar",
   "w": 3,
   "na": true,
   "nb": true
  },
  {
   "a": "alok-talekar",
   "b": "gaurav-aggarwal",
   "w": 3,
   "na": true,
   "nb": true
  },
  {
   "a": "alok-talekar",
   "b": "milind-tambe",
   "w": 3,
   "na": true,
   "nb": true
  },
  {
   "a": "ashish-v-tendulkar",
   "b": "gaurav-aggarwal",
   "w": 3,
   "na": true,
   "nb": true
  },
  {
   "a": "ashish-v-tendulkar",
   "b": "milind-tambe",
   "w": 3,
   "na": true,
   "nb": true
  },
  {
   "a": "ashish-v-tendulkar",
   "b": "xue-ben",
   "w": 2,
   "na": false,
   "nb": true
  },
  {
   "a": "burton-h-singer",
   "b": "chad-r-wells",
   "w": 3,
   "na": true,
   "nb": true
  },
  {
   "a": "burton-h-singer",
   "b": "rita-r-colwell",
   "w": 3,
   "na": true,
   "nb": true
  },
  {
   "a": "chad-r-wells",
   "b": "rita-r-colwell",
   "w": 3,
   "na": true,
   "nb": true
  },
  {
   "a": "gaia-dempsey",
   "b": "juan-cambeiro",
   "w": 3,
   "na": true,
   "nb": true
  },
  {
   "a": "gaia-dempsey",
   "b": "maimuna-s-majumder",
   "w": 2,
   "na": true,
   "nb": false
  },
  {
   "a": "gaia-dempsey",
   "b": "paolo-bocchini",
   "w": 2,
   "na": true,
   "nb": false
  },
  {
   "a": "gaia-dempsey",
   "b": "sylvain-chevalier",
   "w": 2,
   "na": true,
   "nb": false
  },
  {
   "a": "gaia-dempsey",
   "b": "tamay-besiroglu",
   "w": 2,
   "na": true,
   "nb": false
  },
  {
   "a": "gaurav-aggarwal",
   "b": "milind-tambe",
   "w": 3,
   "na": true,
   "nb": true
  },
  {
   "a": "gaurav-aggarwal",
   "b": "xue-ben",
   "w": 2,
   "na": false,
   "nb": true
  },
  {
   "a": "h-vincent-poor",
   "b": "simon-a-levin",
   "w": 3,
   "na": true,
   "nb": true
  },
  {
   "a": "james-schlitt",
   "b": "mark-orr",
   "w": 2,
   "na": true,
   "nb": true
  },
  {
   "a": "juan-cambeiro",
   "b": "maimuna-s-majumder",
   "w": 2,
   "na": true,
   "nb": false
  },
  {
   "a": "juan-cambeiro",
   "b": "paolo-bocchini",
   "w": 2,
   "na": true,
   "nb": false
  },
  {
   "a": "juan-cambeiro",
   "b": "sylvain-chevalier",
   "w": 2,
   "na": true,
   "nb": false
  },
  {
   "a": "juan-cambeiro",
   "b": "tamay-besiroglu",
   "w": 2,
   "na": true,
   "nb": false
  },
  {
   "a": "milind-tambe",
   "b": "xue-ben",
   "w": 2,
   "na": false,
   "nb": true
  },
  {
   "a": "nihesh-rathod",
   "b": "sarath-yasodharan",
   "w": 3,
   "na": true,
   "nb": true
  },
  {
   "a": "qiu-fang-ying",
   "b": "xiaopeng-zhang",
   "w": 2,
   "na": true,
   "nb": true
  },
  {
   "a": "r-muniappan",
   "b": "luke-a-colavito",
   "w": 2,
   "na": true,
   "nb": false
  },
  {
   "a": "r-muniappan",
   "b": "r-asokan",
   "w": 2,
   "na": true,
   "nb": false
  },
  {
   "a": "r-muniappan",
   "b": "sichao-wu",
   "w": 2,
   "na": true,
   "nb": false
  },
  {
   "a": "r-muniappan",
   "b": "v-sridhar",
   "w": 2,
   "na": true,
   "nb": false
  },
  {
   "a": "allison-codi",
   "b": "andrew-a-lover",
   "w": 2,
   "na": true,
   "nb": true
  },
  {
   "a": "allison-codi",
   "b": "maimuna-s-majumder",
   "w": 2,
   "na": true,
   "nb": true
  },
  {
   "a": "allison-codi",
   "b": "paolo-bocchini",
   "w": 2,
   "na": true,
   "nb": true
  },
  {
   "a": "allison-codi",
   "b": "sylvain-chevalier",
   "w": 2,
   "na": true,
   "nb": true
  },
  {
   "a": "allison-codi",
   "b": "tamay-besiroglu",
   "w": 2,
   "na": true,
   "nb": true
  },
  {
   "a": "andrew-a-lover",
   "b": "maimuna-s-majumder",
   "w": 2,
   "na": true,
   "nb": true
  },
  {
   "a": "andrew-a-lover",
   "b": "paolo-bocchini",
   "w": 2,
   "na": true,
   "nb": true
  },
  {
   "a": "andrew-a-lover",
   "b": "sylvain-chevalier",
   "w": 2,
   "na": true,
   "nb": true
  },
  {
   "a": "andrew-a-lover",
   "b": "tamay-besiroglu",
   "w": 2,
   "na": true,
   "nb": true
  },
  {
   "a": "arash-haddadan",
   "b": "aravind-srinivasan",
   "w": 2,
   "na": true,
   "nb": true
  },
  {
   "a": "arash-haddadan",
   "b": "gal-ehrlich",
   "w": 2,
   "na": true,
   "nb": true
  },
  {
   "a": "arash-haddadan",
   "b": "maier-fenster",
   "w": 2,
   "na": true,
   "nb": true
  },
  {
   "a": "aravind-srinivasan",
   "b": "gal-ehrlich",
   "w": 2,
   "na": true,
   "nb": true
  },
  {
   "a": "aravind-srinivasan",
   "b": "maier-fenster",
   "w": 2,
   "na": true,
   "nb": true
  },
  {
   "a": "arup-giri",
   "b": "lalit-prasad-sah",
   "w": 2,
   "na": true,
   "nb": false
  },
  {
   "a": "arup-giri",
   "b": "luke-a-colavito",
   "w": 2,
   "na": true,
   "nb": false
  },
  {
   "a": "arup-giri",
   "b": "r-asokan",
   "w": 2,
   "na": true,
   "nb": false
  },
  {
   "a": "arup-giri",
   "b": "sichao-wu",
   "w": 2,
   "na": true,
   "nb": false
  },
  {
   "a": "arup-giri",
   "b": "v-sridhar",
   "w": 2,
   "na": true,
   "nb": false
  },
  {
   "a": "bowen-shi",
   "b": "lalit-prasad-sah",
   "w": 2,
   "na": true,
   "nb": false
  },
  {
   "a": "bowen-shi",
   "b": "luke-a-colavito",
   "w": 2,
   "na": true,
   "nb": false
  },
  {
   "a": "bowen-shi",
   "b": "r-asokan",
   "w": 2,
   "na": true,
   "nb": false
  },
  {
   "a": "bowen-shi",
   "b": "sichao-wu",
   "w": 2,
   "na": true,
   "nb": false
  },
  {
   "a": "bowen-shi",
   "b": "v-sridhar",
   "w": 2,
   "na": true,
   "nb": false
  },
  {
   "a": "gal-ehrlich",
   "b": "maier-fenster",
   "w": 2,
   "na": true,
   "nb": true
  },
  {
   "a": "george-w-norton",
   "b": "lalit-prasad-sah",
   "w": 2,
   "na": true,
   "nb": false
  },
  {
   "a": "george-w-norton",
   "b": "luke-a-colavito",
   "w": 2,
   "na": true,
   "nb": false
  },
  {
   "a": "george-w-norton",
   "b": "r-asokan",
   "w": 2,
   "na": true,
   "nb": false
  },
  {
   "a": "george-w-norton",
   "b": "sichao-wu",
   "w": 2,
   "na": true,
   "nb": false
  },
  {
   "a": "george-w-norton",
   "b": "v-sridhar",
   "w": 2,
   "na": true,
   "nb": false
  },
  {
   "a": "k-s-nitin",
   "b": "lalit-prasad-sah",
   "w": 2,
   "na": true,
   "nb": true
  },
  {
   "a": "k-s-nitin",
   "b": "luke-a-colavito",
   "w": 2,
   "na": true,
   "nb": true
  },
  {
   "a": "k-s-nitin",
   "b": "r-asokan",
   "w": 2,
   "na": true,
   "nb": true
  },
  {
   "a": "k-s-nitin",
   "b": "sichao-wu",
   "w": 2,
   "na": true,
   "nb": true
  },
  {
   "a": "k-s-nitin",
   "b": "v-sridhar",
   "w": 2,
   "na": true,
   "nb": true
  },
  {
   "a": "lalit-prasad-sah",
   "b": "luke-a-colavito",
   "w": 2,
   "na": true,
   "nb": true
  },
  {
   "a": "lalit-prasad-sah",
   "b": "r-asokan",
   "w": 2,
   "na": true,
   "nb": true
  },
  {
   "a": "lalit-prasad-sah",
   "b": "sichao-wu",
   "w": 2,
   "na": true,
   "nb": true
  },
  {
   "a": "lalit-prasad-sah",
   "b": "v-sridhar",
   "w": 2,
   "na": true,
   "nb": true
  },
  {
   "a": "luke-a-colavito",
   "b": "r-asokan",
   "w": 2,
   "na": true,
   "nb": true
  },
  {
   "a": "luke-a-colavito",
   "b": "sichao-wu",
   "w": 2,
   "na": true,
   "nb": true
  },
  {
   "a": "luke-a-colavito",
   "b": "v-sridhar",
   "w": 2,
   "na": true,
   "nb": true
  },
  {
   "a": "maimuna-s-majumder",
   "b": "paolo-bocchini",
   "w": 2,
   "na": true,
   "nb": true
  },
  {
   "a": "maimuna-s-majumder",
   "b": "sylvain-chevalier",
   "w": 2,
   "na": true,
   "nb": true
  },
  {
   "a": "maimuna-s-majumder",
   "b": "tamay-besiroglu",
   "w": 2,
   "na": true,
   "nb": true
  },
  {
   "a": "paolo-bocchini",
   "b": "sylvain-chevalier",
   "w": 2,
   "na": true,
   "nb": true
  },
  {
   "a": "paolo-bocchini",
   "b": "tamay-besiroglu",
   "w": 2,
   "na": true,
   "nb": true
  },
  {
   "a": "r-asokan",
   "b": "sichao-wu",
   "w": 2,
   "na": true,
   "nb": true
  },
  {
   "a": "r-asokan",
   "b": "v-sridhar",
   "w": 2,
   "na": true,
   "nb": true
  },
  {
   "a": "sichao-wu",
   "b": "v-sridhar",
   "w": 2,
   "na": true,
   "nb": true
  },
  {
   "a": "sylvain-chevalier",
   "b": "tamay-besiroglu",
   "w": 2,
   "na": true,
   "nb": true
  }
 ]
}
